{
  "scrape_info": {
    "timestamp": "2026-01-09T07:19:23.275440+00:00",
    "total_matches": 40,
    "source_url": "https://www.windrawwin.com/predictions/today/"
  },
  "matches": [
    {
      "teams": {
        "home": "Cameroon",
        "away": "Morocco"
      },
      "prediction": {
        "type": "Draw",
        "stake": "Large",
        "score": "1-1"
      },
      "form": {
        "home": [
          "L",
          "W",
          "D",
          "W",
          "W"
        ],
        "away": [
          "W",
          "W",
          "D",
          "W",
          "W"
        ]
      },
      "place_bet": "https://stake.com/?c=Z6Kt1NA0"
    },
    {
      "teams": {
        "home": "Mali",
        "away": "Senegal"
      },
      "prediction": {
        "type": "Away Win",
        "stake": "Small",
        "score": "1-2"
      },
      "form": {
        "home": [
          "D",
          "D",
          "D",
          "D",
          "D"
        ],
        "away": [
          "W",
          "W",
          "D",
          "W",
          "W"
        ]
      },
      "place_bet": "https://refpa3267686.top/L?tag=d_4524740m_1599c_&site=4524740&ad=1599"
    },
    {
      "teams": {
        "home": "Milton Keynes Dons",
        "away": "Oxford Utd"
      },
      "prediction": {
        "type": "Draw",
        "stake": "Large",
        "score": "1-1"
      },
      "form": {
        "home": [
          "W",
          "W",
          "D",
          "L",
          "D"
        ],
        "away": [
          "L",
          "L",
          "W",
          "L",
          "L"
        ]
      },
      "place_bet": "https://stake.com/?c=Z6Kt1NA0"
    },
    {
      "teams": {
        "home": "Port Vale",
        "away": "Fleetwood Town"
      },
      "prediction": {
        "type": "Home Win",
        "stake": "Small",
        "score": "2-1"
      },
      "form": {
        "home": [
          "D",
          "L",
          "L",
          "L",
          "W"
        ],
        "away": [
          "W",
          "W",
          "L",
          "D",
          "L"
        ]
      },
      "place_bet": "https://stake.com/?c=Z6Kt1NA0"
    },
    {
      "teams": {
        "home": "Preston",
        "away": "Wigan"
      },
      "prediction": {
        "type": "Home Win",
        "stake": "Large",
        "score": "2-1"
      },
      "form": {
        "home": [
          "D",
          "D",
          "L",
          "W",
          "W"
        ],
        "away": [
          "L",
          "L",
          "W",
          "D",
          "L"
        ]
      },
      "place_bet": "https://stake.com/?c=Z6Kt1NA0"
    },
    {
      "teams": {
        "home": "Wrexham",
        "away": "Nottingham Forest"
      },
      "prediction": {
        "type": "Draw",
        "stake": "Small",
        "score": "1-1"
      },
      "form": {
        "home": [
          "L",
          "W",
          "W",
          "W",
          "W"
        ],
        "away": [
          "L",
          "L",
          "L",
          "L",
          "W"
        ]
      },
      "place_bet": "https://refpa3267686.top/L?tag=d_4524740m_1599c_&site=4524740&ad=1599"
    },
    {
      "teams": {
        "home": "Ross County",
        "away": "Partick"
      },
      "prediction": {
        "type": "Away Win",
        "stake": "Large",
        "score": "1-2"
      },
      "form": {
        "home": [
          "L",
          "L",
          "L",
          "L",
          "D"
        ],
        "away": [
          "D",
          "L",
          "D",
          "D",
          "W"
        ]
      },
      "place_bet": "https://stake.com/?c=Z6Kt1NA0"
    },
    {
      "teams": {
        "home": "Barry Town",
        "away": "Llanelli"
      },
      "prediction": {
        "type": "Home Win",
        "stake": "Large",
        "score": "2-0"
      },
      "form": {
        "home": [
          "W",
          "D",
          "W",
          "L",
          "L"
        ],
        "away": [
          "D",
          "L",
          "L",
          "L",
          "L"
        ]
      },
      "place_bet": "https://stake.com/?c=Z6Kt1NA0"
    },
    {
      "teams": {
        "home": "Caernarfon Town",
        "away": "Connahs Quay"
      },
      "prediction": {
        "type": "Away Win",
        "stake": "Medium",
        "score": "1-2"
      },
      "form": {
        "home": [
          "D",
          "L",
          "D",
          "L",
          "W"
        ],
        "away": [
          "W",
          "W",
          "W",
          "W",
          "W"
        ]
      },
      "place_bet": "https://refpa3267686.top/L?tag=d_4524740m_1599c_&site=4524740&ad=1599"
    },
    {
      "teams": {
        "home": "Flint Town",
        "away": "Bala Town"
      },
      "prediction": {
        "type": "Home Win",
        "stake": "Large",
        "score": "3-0"
      },
      "form": {
        "home": [
          "D",
          "D",
          "D",
          "L",
          "W"
        ],
        "away": [
          "L",
          "D",
          "L",
          "L",
          "L"
        ]
      },
      "place_bet": "https://refpa3267686.top/L?tag=d_4524740m_1599c_&site=4524740&ad=1599"
    },
    {
      "teams": {
        "home": "Haverfordwest",
        "away": "Briton Ferry"
      },
      "prediction": {
        "type": "Draw",
        "stake": "Large",
        "score": "2-2"
      },
      "form": {
        "home": [
          "L",
          "W",
          "D",
          "W",
          "D"
        ],
        "away": [
          "L",
          "D",
          "L",
          "D",
          "W"
        ]
      },
      "place_bet": "https://refpa3267686.top/L?tag=d_4524740m_1599c_&site=4524740&ad=1599"
    },
    {
      "teams": {
        "home": "Penybont",
        "away": "Cardiff Metropolitan University"
      },
      "prediction": {
        "type": "Away Win",
        "stake": "Small",
        "score": "0-1"
      },
      "form": {
        "home": [
          "W",
          "L",
          "D",
          "D",
          "W"
        ],
        "away": [
          "D",
          "W",
          "D",
          "L",
          "D"
        ]
      },
      "place_bet": "https://stake.com/?c=Z6Kt1NA0"
    },
    {
      "teams": {
        "home": "The New Saints",
        "away": "Colwyn Bay"
      },
      "prediction": {
        "type": "Home Win",
        "stake": "Large",
        "score": "2-0"
      },
      "form": {
        "home": [
          "W",
          "W",
          "W",
          "L",
          "W"
        ],
        "away": [
          "L",
          "W",
          "L",
          "W",
          "L"
        ]
      },
      "place_bet": "https://stake.com/?c=Z6Kt1NA0"
    },
    {
      "teams": {
        "home": "Ascoli",
        "away": "Ternana"
      },
      "prediction": {
        "type": "Away Win",
        "stake": "Small",
        "score": "0-1"
      },
      "form": {
        "home": [
          "D",
          "W",
          "D",
          "D",
          "L"
        ],
        "away": [
          "L",
          "W",
          "W",
          "D",
          "W"
        ]
      },
      "place_bet": "https://stake.com/?c=Z6Kt1NA0"
    },
    {
      "teams": {
        "home": "Audace Cerignola",
        "away": "Potenza"
      },
      "prediction": {
        "type": "Draw",
        "stake": "Small",
        "score": "2-2"
      },
      "form": {
        "home": [
          "W",
          "D",
          "D",
          "L",
          "D"
        ],
        "away": [
          "W",
          "D",
          "D",
          "L",
          "D"
        ]
      },
      "place_bet": "https://refpa3267686.top/L?tag=d_4524740m_1599c_&site=4524740&ad=1599"
    },
    {
      "teams": {
        "home": "Getafe",
        "away": "Real Sociedad"
      },
      "prediction": {
        "type": "Home Win",
        "stake": "Medium",
        "score": "1-0"
      },
      "form": {
        "home": [
          "W",
          "L",
          "L",
          "L",
          "D"
        ],
        "away": [
          "L",
          "L",
          "L",
          "D",
          "D"
        ]
      },
      "place_bet": "https://refpa3267686.top/L?tag=d_4524740m_1599c_&site=4524740&ad=1599"
    },
    {
      "teams": {
        "home": "Cadiz",
        "away": "Sporting Gijon"
      },
      "prediction": {
        "type": "Home Win",
        "stake": "Small",
        "score": "1-0"
      },
      "form": {
        "home": [
          "W",
          "L",
          "W",
          "W",
          "D"
        ],
        "away": [
          "D",
          "W",
          "W",
          "W",
          "L"
        ]
      },
      "place_bet": "https://refpa3267686.top/L?tag=d_4524740m_1599c_&site=4524740&ad=1599"
    },
    {
      "teams": {
        "home": "Eintracht Frankfurt",
        "away": "Borussia Dortmund"
      },
      "prediction": {
        "type": "Away Win",
        "stake": "Large",
        "score": "0-1"
      },
      "form": {
        "home": [
          "W",
          "D",
          "L",
          "W",
          "D"
        ],
        "away": [
          "D",
          "W",
          "W",
          "D",
          "W"
        ]
      },
      "place_bet": "https://refpa3267686.top/L?tag=d_4524740m_1599c_&site=4524740&ad=1599"
    },
    {
      "teams": {
        "home": "Amed Sportif Faaliyetler",
        "away": "Corum"
      },
      "prediction": {
        "type": "Home Win",
        "stake": "Large",
        "score": "3-0"
      },
      "form": {
        "home": [
          "W",
          "W",
          "W",
          "D",
          "W"
        ],
        "away": [
          "L",
          "W",
          "D",
          "W",
          "L"
        ]
      },
      "place_bet": "https://refpa3267686.top/L?tag=d_4524740m_1599c_&site=4524740&ad=1599"
    },
    {
      "teams": {
        "home": "Vanspor FK",
        "away": "Boluspor"
      },
      "prediction": {
        "type": "Away Win",
        "stake": "Large",
        "score": "0-1"
      },
      "form": {
        "home": [
          "L",
          "L",
          "L",
          "W",
          "W"
        ],
        "away": [
          "L",
          "W",
          "W",
          "L",
          "W"
        ]
      },
      "place_bet": "https://refpa3267686.top/L?tag=d_4524740m_1599c_&site=4524740&ad=1599"
    },
    {
      "teams": {
        "home": "Limassol",
        "away": "Omonia Nicosia"
      },
      "prediction": {
        "type": "Draw",
        "stake": "Medium",
        "score": "1-1"
      },
      "form": {
        "home": [
          "D",
          "W",
          "D",
          "L",
          "W"
        ],
        "away": [
          "W",
          "W",
          "D",
          "W",
          "W"
        ]
      },
      "place_bet": "https://stake.com/?c=Z6Kt1NA0"
    },
    {
      "teams": {
        "home": "Belouizdad",
        "away": "Kabylie"
      },
      "prediction": {
        "type": "Home Win",
        "stake": "Medium",
        "score": "2-0"
      },
      "form": {
        "home": [
          "L",
          "W",
          "W",
          "D",
          "W"
        ],
        "away": [
          "L",
          "L",
          "W",
          "D",
          "D"
        ]
      },
      "place_bet": "https://refpa3267686.top/L?tag=d_4524740m_1599c_&site=4524740&ad=1599"
    },
    {
      "teams": {
        "home": "Chlef",
        "away": "MC Alger"
      },
      "prediction": {
        "type": "Away Win",
        "stake": "Large",
        "score": "0-1"
      },
      "form": {
        "home": [
          "L",
          "L",
          "L",
          "W",
          "L"
        ],
        "away": [
          "L",
          "W",
          "W",
          "D",
          "W"
        ]
      },
      "place_bet": "https://stake.com/?c=Z6Kt1NA0"
    },
    {
      "teams": {
        "home": "CS Constantine",
        "away": "JS Saoura"
      },
      "prediction": {
        "type": "Home Win",
        "stake": "Medium",
        "score": "2-0"
      },
      "form": {
        "home": [
          "L",
          "W",
          "W",
          "D",
          "L"
        ],
        "away": [
          "L",
          "L",
          "L",
          "W",
          "W"
        ]
      },
      "place_bet": "https://refpa3267686.top/L?tag=d_4524740m_1599c_&site=4524740&ad=1599"
    },
    {
      "teams": {
        "home": "MB Rouissat",
        "away": "Khenchela"
      },
      "prediction": {
        "type": "Away Win",
        "stake": "Large",
        "score": "0-1"
      },
      "form": {
        "home": [
          "L",
          "W",
          "L",
          "L",
          "D"
        ],
        "away": [
          "L",
          "W",
          "W",
          "W",
          "D"
        ]
      },
      "place_bet": "https://refpa3267686.top/L?tag=d_4524740m_1599c_&site=4524740&ad=1599"
    },
    {
      "teams": {
        "home": "Eleven Wonders",
        "away": "Basake Holy Stars"
      },
      "prediction": {
        "type": "Away Win",
        "stake": "Medium",
        "score": "0-1"
      },
      "form": {
        "home": [
          "L",
          "L",
          "L",
          "L",
          "L"
        ],
        "away": [
          "D",
          "W",
          "D",
          "W",
          "L"
        ]
      },
      "place_bet": "https://refpa3267686.top/L?tag=d_4524740m_1599c_&site=4524740&ad=1599"
    },
    {
      "teams": {
        "home": "Persita Tangerang",
        "away": "Borneo Samarinda"
      },
      "prediction": {
        "type": "Home Win",
        "stake": "Medium",
        "score": "2-0"
      },
      "form": {
        "home": [
          "D",
          "L",
          "W",
          "W",
          "W"
        ],
        "away": [
          "L",
          "L",
          "D",
          "L",
          "W"
        ]
      },
      "place_bet": "https://refpa3267686.top/L?tag=d_4524740m_1599c_&site=4524740&ad=1599"
    },
    {
      "teams": {
        "home": "PSM Makassar",
        "away": "Bali United"
      },
      "prediction": {
        "type": "Away Win",
        "stake": "Large",
        "score": "0-1"
      },
      "form": {
        "home": [
          "W",
          "D",
          "L",
          "L",
          "L"
        ],
        "away": [
          "D",
          "W",
          "W",
          "D",
          "W"
        ]
      },
      "place_bet": "https://stake.com/?c=Z6Kt1NA0"
    },
    {
      "teams": {
        "home": "Negeri Sembilan",
        "away": "Johor"
      },
      "prediction": {
        "type": "Away Win",
        "stake": "Large",
        "score": "0-1"
      },
      "form": {
        "home": [
          "D",
          "D",
          "L",
          "D",
          "W"
        ],
        "away": [
          "W",
          "W",
          "W",
          "W",
          "W"
        ]
      },
      "place_bet": "https://stake.com/?c=Z6Kt1NA0"
    },
    {
      "teams": {
        "home": "Sabah",
        "away": "Kuala Lumpur"
      },
      "prediction": {
        "type": "Away Win",
        "stake": "Large",
        "score": "1-2"
      },
      "form": {
        "home": [
          "L",
          "W",
          "W",
          "L",
          "W"
        ],
        "away": [
          "W",
          "L",
          "D",
          "D",
          "W"
        ]
      },
      "place_bet": "https://refpa3267686.top/L?tag=d_4524740m_1599c_&site=4524740&ad=1599"
    },
    {
      "teams": {
        "home": "Uthai Thani",
        "away": "Buriram United"
      },
      "prediction": {
        "type": "Away Win",
        "stake": "Large",
        "score": "1-2"
      },
      "form": {
        "home": [
          "W",
          "D",
          "W",
          "L",
          "W"
        ],
        "away": [
          "W",
          "W",
          "W",
          "W",
          "D"
        ]
      },
      "place_bet": "https://stake.com/?c=Z6Kt1NA0"
    },
    {
      "teams": {
        "home": "Kenya Commercial Bank",
        "away": "Kenya Police"
      },
      "prediction": {
        "type": "Home Win",
        "stake": "Medium",
        "score": "1-0"
      },
      "form": {
        "home": [
          "D",
          "W",
          "W",
          "W",
          "L"
        ],
        "away": [
          "L",
          "W",
          "D",
          "L",
          "D"
        ]
      },
      "place_bet": "https://stake.com/?c=Z6Kt1NA0"
    },
    {
      "teams": {
        "home": "Sofapaka",
        "away": "Bidco United"
      },
      "prediction": {
        "type": "Away Win",
        "stake": "Medium",
        "score": "0-1"
      },
      "form": {
        "home": [
          "D",
          "L",
          "L",
          "L",
          "D"
        ],
        "away": [
          "L",
          "L",
          "D",
          "L",
          "L"
        ]
      },
      "place_bet": "https://stake.com/?c=Z6Kt1NA0"
    },
    {
      "teams": {
        "home": "Brisbane Roar",
        "away": "Auckland FC"
      },
      "prediction": {
        "type": "Away Win",
        "stake": "Large",
        "score": "0-1"
      },
      "form": {
        "home": [
          "D",
          "L",
          "W",
          "L",
          "L"
        ],
        "away": [
          "W",
          "W",
          "W",
          "L",
          "D"
        ]
      },
      "place_bet": "https://refpa3267686.top/L?tag=d_4524740m_1599c_&site=4524740&ad=1599"
    },
    {
      "teams": {
        "home": "Maccabi Netanya",
        "away": "Hapoel Jerusalem"
      },
      "prediction": {
        "type": "Draw",
        "stake": "Large",
        "score": "2-2"
      },
      "form": {
        "home": [
          "W",
          "L",
          "D",
          "L",
          "L"
        ],
        "away": [
          "D",
          "W",
          "L",
          "L",
          "L"
        ]
      },
      "place_bet": "https://stake.com/?c=Z6Kt1NA0"
    },
    {
      "teams": {
        "home": "Al Khalidiyah",
        "away": "Al Najma"
      },
      "prediction": {
        "type": "Home Win",
        "stake": "Medium",
        "score": "2-0"
      },
      "form": {
        "home": [
          "W",
          "W",
          "W",
          "W",
          "W"
        ],
        "away": [
          "W",
          "D",
          "W",
          "L",
          "W"
        ]
      },
      "place_bet": "https://refpa3267686.top/L?tag=d_4524740m_1599c_&site=4524740&ad=1599"
    },
    {
      "teams": {
        "home": "Bahrain SC",
        "away": "Al Rifaa"
      },
      "prediction": {
        "type": "Draw",
        "stake": "Medium",
        "score": "1-1"
      },
      "form": {
        "home": [
          "W",
          "L",
          "W",
          "L",
          "L"
        ],
        "away": [
          "L",
          "W",
          "W",
          "W",
          "W"
        ]
      },
      "place_bet": "https://stake.com/?c=Z6Kt1NA0"
    },
    {
      "teams": {
        "home": "Al Khaleej",
        "away": "Damac"
      },
      "prediction": {
        "type": "Draw",
        "stake": "Small",
        "score": "2-2"
      },
      "form": {
        "home": [
          "W",
          "L",
          "L",
          "L",
          "D"
        ],
        "away": [
          "D",
          "D",
          "D",
          "W",
          "L"
        ]
      },
      "place_bet": "https://refpa3267686.top/L?tag=d_4524740m_1599c_&site=4524740&ad=1599"
    },
    {
      "teams": {
        "home": "Al Kholood",
        "away": "Ittihad Jeddah"
      },
      "prediction": {
        "type": "Draw",
        "stake": "Medium",
        "score": "2-2"
      },
      "form": {
        "home": [
          "L",
          "L",
          "L",
          "L",
          "W"
        ],
        "away": [
          "L",
          "W",
          "W",
          "W",
          "W"
        ]
      },
      "place_bet": "https://stake.com/?c=Z6Kt1NA0"
    },
    {
      "teams": {
        "home": "Al Taawon",
        "away": "Al Shabab Riyadh"
      },
      "prediction": {
        "type": "Home Win",
        "stake": "Medium",
        "score": "2-0"
      },
      "form": {
        "home": [
          "W",
          "D",
          "W",
          "W",
          "L"
        ],
        "away": [
          "D",
          "D",
          "L",
          "L",
          "L"
        ]
      },
      "place_bet": "https://stake.com/?c=Z6Kt1NA0"
    }
  ]
}