{
  "scrape_info": {
    "timestamp": "2025-08-08T06:28:31.377761+00:00",
    "total_matches": 122,
    "source_url": "https://www.windrawwin.com/predictions/today/"
  },
  "matches": [
    {
      "teams": {
        "home": "Birmingham",
        "away": "Ipswich"
      },
      "prediction": {
        "type": "Home Win",
        "stake": "Medium",
        "score": "2-0"
      },
      "form": {
        "home": [
          "W",
          "W",
          "W",
          "W",
          "W"
        ],
        "away": [
          "L",
          "D",
          "L",
          "L",
          "L"
        ]
      },
      "place_bet": "stake.com/?c=Z6Kt1NA0"
    },
    {
      "teams": {
        "home": "Ross County",
        "away": "St Johnstone"
      },
      "prediction": {
        "type": "Away Win",
        "stake": "Small",
        "score": "1-3"
      },
      "form": {
        "home": [
          "D",
          "W",
          "W",
          "L",
          "D"
        ],
        "away": [
          "W",
          "W",
          "W",
          "W",
          "W"
        ]
      },
      "place_bet": "https://refpa3267686.top/L?tag=d_4524740m_1599c_&site=4524740&ad=1599"
    },
    {
      "teams": {
        "home": "Bala Town",
        "away": "Flint Town"
      },
      "prediction": {
        "type": "Home Win",
        "stake": "Small",
        "score": "1-0"
      },
      "form": {
        "home": [
          "L",
          "D",
          "L",
          "W",
          "L"
        ],
        "away": [
          "L",
          "W",
          "W",
          "W",
          "W"
        ]
      },
      "place_bet": "https://refpa3267686.top/L?tag=d_4524740m_1599c_&site=4524740&ad=1599"
    },
    {
      "teams": {
        "home": "Haverfordwest",
        "away": "Penybont"
      },
      "prediction": {
        "type": "Away Win",
        "stake": "Small",
        "score": "0-1"
      },
      "form": {
        "home": [
          "D",
          "D",
          "L",
          "W",
          "L"
        ],
        "away": [
          "W",
          "W",
          "W",
          "L",
          "L"
        ]
      },
      "place_bet": "stake.com/?c=Z6Kt1NA0"
    },
    {
      "teams": {
        "home": "Llanelli",
        "away": "Barry Town"
      },
      "prediction": {
        "type": "Away Win",
        "stake": "Small",
        "score": "1-3"
      },
      "form": {
        "home": [
          "L",
          "L",
          "L",
          "L",
          "L"
        ],
        "away": [
          "L",
          "W",
          "W",
          "W",
          "L"
        ]
      },
      "place_bet": "https://refpa3267686.top/L?tag=d_4524740m_1599c_&site=4524740&ad=1599"
    },
    {
      "teams": {
        "home": "Nurnberg",
        "away": "Darmstadt"
      },
      "prediction": {
        "type": "Away Win",
        "stake": "Small",
        "score": "1-3"
      },
      "form": {
        "home": [
          "D",
          "L",
          "L",
          "W",
          "L"
        ],
        "away": [
          "D",
          "L",
          "L",
          "W",
          "W"
        ]
      },
      "place_bet": "stake.com/?c=Z6Kt1NA0"
    },
    {
      "teams": {
        "home": "Preussen Munster",
        "away": "Paderborn"
      },
      "prediction": {
        "type": "Away Win",
        "stake": "Small",
        "score": "0-1"
      },
      "form": {
        "home": [
          "D",
          "W",
          "W",
          "D",
          "L"
        ],
        "away": [
          "D",
          "W",
          "W",
          "L",
          "W"
        ]
      },
      "place_bet": "https://refpa3267686.top/L?tag=d_4524740m_1599c_&site=4524740&ad=1599"
    },
    {
      "teams": {
        "home": "Schweinfurt",
        "away": "Cottbus"
      },
      "prediction": {
        "type": "Away Win",
        "stake": "Small",
        "score": "0-1"
      },
      "form": {
        "home": [
          "D",
          "W",
          "L",
          "W",
          "L"
        ],
        "away": [
          "D",
          "L",
          "W",
          "L",
          "D"
        ]
      },
      "place_bet": "stake.com/?c=Z6Kt1NA0"
    },
    {
      "teams": {
        "home": "Oldenburg",
        "away": "Lubeck"
      },
      "prediction": {
        "type": "Away Win",
        "stake": "Small",
        "score": "1-3"
      },
      "form": {
        "home": [
          "W",
          "L",
          "L",
          "L",
          "W"
        ],
        "away": [
          "W",
          "W",
          "L",
          "W",
          "L"
        ]
      },
      "place_bet": "https://refpa3267686.top/L?tag=d_4524740m_1599c_&site=4524740&ad=1599"
    },
    {
      "teams": {
        "home": "Altglienicke",
        "away": "Carl Zeiss Jena"
      },
      "prediction": {
        "type": "Home Win",
        "stake": "Large",
        "score": "1-0"
      },
      "form": {
        "home": [
          "W",
          "L",
          "D",
          "W",
          "L"
        ],
        "away": [
          "W",
          "L",
          "W",
          "W",
          "W"
        ]
      },
      "place_bet": "stake.com/?c=Z6Kt1NA0"
    },
    {
      "teams": {
        "home": "Hertha Berlin II",
        "away": "Eilenburg"
      },
      "prediction": {
        "type": "Home Win",
        "stake": "Small",
        "score": "1-0"
      },
      "form": {
        "home": [
          "W",
          "D",
          "L",
          "L",
          "L"
        ],
        "away": [
          "L",
          "D",
          "D",
          "D",
          "W"
        ]
      },
      "place_bet": "stake.com/?c=Z6Kt1NA0"
    },
    {
      "teams": {
        "home": "SC Paderborn 07 II",
        "away": "FC Koln II"
      },
      "prediction": {
        "type": "Away Win",
        "stake": "Small",
        "score": "0-1"
      },
      "form": {
        "home": [
          "W",
          "L",
          "D",
          "W",
          "D"
        ],
        "away": [
          "L",
          "W",
          "D",
          "L",
          "W"
        ]
      },
      "place_bet": "https://refpa3267686.top/L?tag=d_4524740m_1599c_&site=4524740&ad=1599"
    },
    {
      "teams": {
        "home": "Kickers Offenbach",
        "away": "Bayern Alzenau"
      },
      "prediction": {
        "type": "Home Win",
        "stake": "Large",
        "score": "2-0"
      },
      "form": {
        "home": [
          "D",
          "W",
          "D",
          "W",
          "W"
        ],
        "away": [
          "D",
          "L",
          "L",
          "L",
          "L"
        ]
      },
      "place_bet": "https://refpa3267686.top/L?tag=d_4524740m_1599c_&site=4524740&ad=1599"
    },
    {
      "teams": {
        "home": "Aubstadt",
        "away": "FC Memmingen"
      },
      "prediction": {
        "type": "Home Win",
        "stake": "Large",
        "score": "1-0"
      },
      "form": {
        "home": [
          "L",
          "D",
          "W",
          "L",
          "W"
        ],
        "away": [
          "W",
          "L",
          "W",
          "W",
          "L"
        ]
      },
      "place_bet": "stake.com/?c=Z6Kt1NA0"
    },
    {
      "teams": {
        "home": "Augsburg II",
        "away": "Unterhaching"
      },
      "prediction": {
        "type": "Away Win",
        "stake": "Small",
        "score": "1-2"
      },
      "form": {
        "home": [
          "L",
          "L",
          "L",
          "L",
          "L"
        ],
        "away": [
          "L",
          "L",
          "L",
          "W",
          "W"
        ]
      },
      "place_bet": "https://refpa3267686.top/L?tag=d_4524740m_1599c_&site=4524740&ad=1599"
    },
    {
      "teams": {
        "home": "Bayern Munich II",
        "away": "Schwaben Augsburg"
      },
      "prediction": {
        "type": "Home Win",
        "stake": "Small",
        "score": "2-0"
      },
      "form": {
        "home": [
          "D",
          "W",
          "D",
          "W",
          "W"
        ],
        "away": [
          "L",
          "L",
          "D",
          "L",
          "L"
        ]
      },
      "place_bet": "https://refpa3267686.top/L?tag=d_4524740m_1599c_&site=4524740&ad=1599"
    },
    {
      "teams": {
        "home": "Buchbach",
        "away": "FC Kickers Wurzburg"
      },
      "prediction": {
        "type": "Home Win",
        "stake": "Medium",
        "score": "2-0"
      },
      "form": {
        "home": [
          "W",
          "D",
          "W",
          "W",
          "L"
        ],
        "away": [
          "L",
          "D",
          "W",
          "W",
          "W"
        ]
      },
      "place_bet": "https://refpa3267686.top/L?tag=d_4524740m_1599c_&site=4524740&ad=1599"
    },
    {
      "teams": {
        "home": "Illertissen",
        "away": "Greuther Furth II"
      },
      "prediction": {
        "type": "Away Win",
        "stake": "Small",
        "score": "1-3"
      },
      "form": {
        "home": [
          "D",
          "L",
          "L",
          "L",
          "W"
        ],
        "away": [
          "W",
          "D",
          "W",
          "W",
          "L"
        ]
      },
      "place_bet": "https://refpa3267686.top/L?tag=d_4524740m_1599c_&site=4524740&ad=1599"
    },
    {
      "teams": {
        "home": "VfB Eichstatt",
        "away": "Hankofen Hailing"
      },
      "prediction": {
        "type": "Home Win",
        "stake": "Small",
        "score": "1-0"
      },
      "form": {
        "home": [
          "L",
          "D",
          "D",
          "L",
          "W"
        ],
        "away": [
          "L",
          "W",
          "D",
          "L",
          "W"
        ]
      },
      "place_bet": "https://refpa3267686.top/L?tag=d_4524740m_1599c_&site=4524740&ad=1599"
    },
    {
      "teams": {
        "home": "Viktoria Aschaffenburg",
        "away": "SpVgg Bayreuth"
      },
      "prediction": {
        "type": "Home Win",
        "stake": "Large",
        "score": "1-0"
      },
      "form": {
        "home": [
          "W",
          "L",
          "W",
          "L",
          "L"
        ],
        "away": [
          "L",
          "L",
          "L",
          "W",
          "L"
        ]
      },
      "place_bet": "https://refpa3267686.top/L?tag=d_4524740m_1599c_&site=4524740&ad=1599"
    },
    {
      "teams": {
        "home": "Pau",
        "away": "Annecy Fc"
      },
      "prediction": {
        "type": "Away Win",
        "stake": "Small",
        "score": "0-1"
      },
      "form": {
        "home": [
          "D",
          "D",
          "W",
          "L",
          "L"
        ],
        "away": [
          "W",
          "D",
          "W",
          "L",
          "W"
        ]
      },
      "place_bet": "https://refpa3267686.top/L?tag=d_4524740m_1599c_&site=4524740&ad=1599"
    },
    {
      "teams": {
        "home": "Troyes",
        "away": "Grenoble"
      },
      "prediction": {
        "type": "Draw",
        "stake": "Medium",
        "score": "1-1"
      },
      "form": {
        "home": [
          "D",
          "W",
          "W",
          "L",
          "W"
        ],
        "away": [
          "L",
          "L",
          "W",
          "W",
          "L"
        ]
      },
      "place_bet": "stake.com/?c=Z6Kt1NA0"
    },
    {
      "teams": {
        "home": "Bourg Peronnas",
        "away": "AC Ajaccio"
      },
      "prediction": {
        "type": "Home Win",
        "stake": "Medium",
        "score": "1-0"
      },
      "form": {
        "home": [
          "D",
          "L",
          "D",
          "W",
          "W"
        ],
        "away": [
          "D",
          "D",
          "L",
          "W",
          "L"
        ]
      },
      "place_bet": "stake.com/?c=Z6Kt1NA0"
    },
    {
      "teams": {
        "home": "Caen",
        "away": "Aubagne FC"
      },
      "prediction": {
        "type": "Away Win",
        "stake": "Small",
        "score": "1-3"
      },
      "form": {
        "home": [
          "D",
          "L",
          "L",
          "D",
          "L"
        ],
        "away": [
          "L",
          "W",
          "W",
          "W",
          "L"
        ]
      },
      "place_bet": "stake.com/?c=Z6Kt1NA0"
    },
    {
      "teams": {
        "home": "Chateauroux",
        "away": "Valenciennes"
      },
      "prediction": {
        "type": "Home Win",
        "stake": "Medium",
        "score": "2-0"
      },
      "form": {
        "home": [
          "W",
          "L",
          "D",
          "W",
          "D"
        ],
        "away": [
          "D",
          "L",
          "D",
          "L",
          "W"
        ]
      },
      "place_bet": "https://refpa3267686.top/L?tag=d_4524740m_1599c_&site=4524740&ad=1599"
    },
    {
      "teams": {
        "home": "Le Puy",
        "away": "Sochaux"
      },
      "prediction": {
        "type": "Home Win",
        "stake": "Medium",
        "score": "2-0"
      },
      "form": {
        "home": [
          "L",
          "W",
          "W",
          "W",
          "L"
        ],
        "away": [
          "L",
          "L",
          "W",
          "L",
          "L"
        ]
      },
      "place_bet": "stake.com/?c=Z6Kt1NA0"
    },
    {
      "teams": {
        "home": "Orleans",
        "away": "Dijon"
      },
      "prediction": {
        "type": "Home Win",
        "stake": "Small",
        "score": "1-0"
      },
      "form": {
        "home": [
          "W",
          "L",
          "L",
          "L",
          "W"
        ],
        "away": [
          "W",
          "W",
          "D",
          "L",
          "L"
        ]
      },
      "place_bet": "https://refpa3267686.top/L?tag=d_4524740m_1599c_&site=4524740&ad=1599"
    },
    {
      "teams": {
        "home": "Paris 13 Atletico",
        "away": "Quevilly Rouen"
      },
      "prediction": {
        "type": "Draw",
        "stake": "Medium",
        "score": "1-1"
      },
      "form": {
        "home": [
          "L",
          "D",
          "D",
          "D",
          "W"
        ],
        "away": [
          "W",
          "L",
          "L",
          "W",
          "W"
        ]
      },
      "place_bet": "https://refpa3267686.top/L?tag=d_4524740m_1599c_&site=4524740&ad=1599"
    },
    {
      "teams": {
        "home": "Rouen",
        "away": "FC Fleury 91"
      },
      "prediction": {
        "type": "Away Win",
        "stake": "Small",
        "score": "0-1"
      },
      "form": {
        "home": [
          "W",
          "L",
          "D",
          "D",
          "D"
        ],
        "away": [
          "W",
          "D",
          "D",
          "W",
          "D"
        ]
      },
      "place_bet": "https://refpa3267686.top/L?tag=d_4524740m_1599c_&site=4524740&ad=1599"
    },
    {
      "teams": {
        "home": "Stade Briochin",
        "away": "FC Versailles 78"
      },
      "prediction": {
        "type": "Home Win",
        "stake": "Small",
        "score": "1-0"
      },
      "form": {
        "home": [
          "D",
          "W",
          "D",
          "W",
          "L"
        ],
        "away": [
          "L",
          "L",
          "W",
          "W",
          "L"
        ]
      },
      "place_bet": "https://refpa3267686.top/L?tag=d_4524740m_1599c_&site=4524740&ad=1599"
    },
    {
      "teams": {
        "home": "Villefranche Beaujolais",
        "away": "Concarneau"
      },
      "prediction": {
        "type": "Home Win",
        "stake": "Large",
        "score": "1-0"
      },
      "form": {
        "home": [
          "L",
          "L",
          "D",
          "D",
          "L"
        ],
        "away": [
          "D",
          "D",
          "W",
          "W",
          "L"
        ]
      },
      "place_bet": "https://refpa3267686.top/L?tag=d_4524740m_1599c_&site=4524740&ad=1599"
    },
    {
      "teams": {
        "home": "Fortuna Sittard",
        "away": "Go Ahead Eagles"
      },
      "prediction": {
        "type": "Home Win",
        "stake": "Small",
        "score": "1-0"
      },
      "form": {
        "home": [
          "W",
          "L",
          "W",
          "D",
          "D"
        ],
        "away": [
          "D",
          "L",
          "D",
          "W",
          "L"
        ]
      },
      "place_bet": "stake.com/?c=Z6Kt1NA0"
    },
    {
      "teams": {
        "home": "De Graafschap",
        "away": "VVV Venlo"
      },
      "prediction": {
        "type": "Home Win",
        "stake": "Medium",
        "score": "1-0"
      },
      "form": {
        "home": [
          "L",
          "W",
          "W",
          "D",
          "L"
        ],
        "away": [
          "W",
          "D",
          "W",
          "L",
          "L"
        ]
      },
      "place_bet": "stake.com/?c=Z6Kt1NA0"
    },
    {
      "teams": {
        "home": "FC Den Bosch",
        "away": "Jong Ajax"
      },
      "prediction": {
        "type": "Away Win",
        "stake": "Small",
        "score": "0-1"
      },
      "form": {
        "home": [
          "L",
          "W",
          "D",
          "D",
          "L"
        ],
        "away": [
          "D",
          "L",
          "W",
          "L",
          "D"
        ]
      },
      "place_bet": "https://refpa3267686.top/L?tag=d_4524740m_1599c_&site=4524740&ad=1599"
    },
    {
      "teams": {
        "home": "FC Dordrecht",
        "away": "Cambuur Leeuwarden"
      },
      "prediction": {
        "type": "Away Win",
        "stake": "Medium",
        "score": "0-2"
      },
      "form": {
        "home": [
          "W",
          "D",
          "W",
          "W",
          "L"
        ],
        "away": [
          "W",
          "W",
          "W",
          "L",
          "D"
        ]
      },
      "place_bet": "https://refpa3267686.top/L?tag=d_4524740m_1599c_&site=4524740&ad=1599"
    },
    {
      "teams": {
        "home": "FC Eindhoven",
        "away": "FC Utrecht II"
      },
      "prediction": {
        "type": "Home Win",
        "stake": "Small",
        "score": "1-0"
      },
      "form": {
        "home": [
          "W",
          "L",
          "W",
          "L",
          "W"
        ],
        "away": [
          "L",
          "L",
          "L",
          "W",
          "L"
        ]
      },
      "place_bet": "https://refpa3267686.top/L?tag=d_4524740m_1599c_&site=4524740&ad=1599"
    },
    {
      "teams": {
        "home": "TOP Oss",
        "away": "MVV Maastricht"
      },
      "prediction": {
        "type": "Draw",
        "stake": "Medium",
        "score": "1-1"
      },
      "form": {
        "home": [
          "L",
          "W",
          "L",
          "D",
          "D"
        ],
        "away": [
          "L",
          "W",
          "L",
          "W",
          "L"
        ]
      },
      "place_bet": "https://refpa3267686.top/L?tag=d_4524740m_1599c_&site=4524740&ad=1599"
    },
    {
      "teams": {
        "home": "Casa Pia Atletico",
        "away": "Sporting Lisbon"
      },
      "prediction": {
        "type": "Away Win",
        "stake": "Large",
        "score": "1-3"
      },
      "form": {
        "home": [
          "D",
          "L",
          "D",
          "W",
          "L"
        ],
        "away": [
          "W",
          "W",
          "W",
          "D",
          "W"
        ]
      },
      "place_bet": "https://refpa3267686.top/L?tag=d_4524740m_1599c_&site=4524740&ad=1599"
    },
    {
      "teams": {
        "home": "Derry City",
        "away": "Cork"
      },
      "prediction": {
        "type": "Home Win",
        "stake": "Large",
        "score": "3-0"
      },
      "form": {
        "home": [
          "W",
          "W",
          "L",
          "D",
          "L"
        ],
        "away": [
          "D",
          "L",
          "L",
          "L",
          "W"
        ]
      },
      "place_bet": "stake.com/?c=Z6Kt1NA0"
    },
    {
      "teams": {
        "home": "Drogheda Utd",
        "away": "Waterford"
      },
      "prediction": {
        "type": "Home Win",
        "stake": "Medium",
        "score": "2-0"
      },
      "form": {
        "home": [
          "W",
          "D",
          "L",
          "W",
          "W"
        ],
        "away": [
          "L",
          "L",
          "W",
          "W",
          "L"
        ]
      },
      "place_bet": "https://refpa3267686.top/L?tag=d_4524740m_1599c_&site=4524740&ad=1599"
    },
    {
      "teams": {
        "home": "Bray",
        "away": "Cobh Ramblers"
      },
      "prediction": {
        "type": "Home Win",
        "stake": "Small",
        "score": "2-1"
      },
      "form": {
        "home": [
          "W",
          "W",
          "W",
          "W",
          "D"
        ],
        "away": [
          "W",
          "L",
          "D",
          "W",
          "W"
        ]
      },
      "place_bet": "stake.com/?c=Z6Kt1NA0"
    },
    {
      "teams": {
        "home": "Dundalk",
        "away": "Athlone Town"
      },
      "prediction": {
        "type": "Home Win",
        "stake": "Large",
        "score": "3-0"
      },
      "form": {
        "home": [
          "W",
          "L",
          "W",
          "W",
          "W"
        ],
        "away": [
          "L",
          "D",
          "D",
          "L",
          "L"
        ]
      },
      "place_bet": "https://refpa3267686.top/L?tag=d_4524740m_1599c_&site=4524740&ad=1599"
    },
    {
      "teams": {
        "home": "Kerry",
        "away": "Finn Harps"
      },
      "prediction": {
        "type": "Draw",
        "stake": "Large",
        "score": "1-1"
      },
      "form": {
        "home": [
          "L",
          "L",
          "L",
          "W",
          "D"
        ],
        "away": [
          "D",
          "L",
          "D",
          "L",
          "D"
        ]
      },
      "place_bet": "https://refpa3267686.top/L?tag=d_4524740m_1599c_&site=4524740&ad=1599"
    },
    {
      "teams": {
        "home": "UCD",
        "away": "Wexford Youths"
      },
      "prediction": {
        "type": "Draw",
        "stake": "Small",
        "score": "1-1"
      },
      "form": {
        "home": [
          "D",
          "W",
          "W",
          "L",
          "W"
        ],
        "away": [
          "L",
          "D",
          "L",
          "W",
          "L"
        ]
      },
      "place_bet": "https://refpa3267686.top/L?tag=d_4524740m_1599c_&site=4524740&ad=1599"
    },
    {
      "teams": {
        "home": "Dynamo Makhachkala",
        "away": "Akron Tolyatti"
      },
      "prediction": {
        "type": "Away Win",
        "stake": "Small",
        "score": "0-1"
      },
      "form": {
        "home": [
          "D",
          "D",
          "L",
          "D",
          "W"
        ],
        "away": [
          "L",
          "L",
          "D",
          "W",
          "D"
        ]
      },
      "place_bet": "https://refpa3267686.top/L?tag=d_4524740m_1599c_&site=4524740&ad=1599"
    },
    {
      "teams": {
        "home": "St Truidense",
        "away": "Dender"
      },
      "prediction": {
        "type": "Home Win",
        "stake": "Large",
        "score": "2-0"
      },
      "form": {
        "home": [
          "W",
          "D",
          "D",
          "D",
          "W"
        ],
        "away": []
      },
      "place_bet": "stake.com/?c=Z6Kt1NA0"
    },
    {
      "teams": {
        "home": "Olympic Charleroi",
        "away": "Jeugd KAA Gent B"
      },
      "prediction": {
        "type": "Draw",
        "stake": "Medium",
        "score": "1-1"
      },
      "form": {
        "home": [],
        "away": []
      },
      "place_bet": "stake.com/?c=Z6Kt1NA0"
    },
    {
      "teams": {
        "home": "RFC Seraing",
        "away": "Beerschot"
      },
      "prediction": {
        "type": "Draw",
        "stake": "Medium",
        "score": "1-1"
      },
      "form": {
        "home": [
          "D",
          "L",
          "D",
          "L",
          "L"
        ],
        "away": [
          "L",
          "L",
          "W",
          "L",
          "W"
        ]
      },
      "place_bet": "stake.com/?c=Z6Kt1NA0"
    },
    {
      "teams": {
        "home": "Ceske Budejovice",
        "away": "FC Vlasim"
      },
      "prediction": {
        "type": "Away Win",
        "stake": "Small",
        "score": "1-3"
      },
      "form": {
        "home": [
          "L",
          "L",
          "L",
          "D",
          "L"
        ],
        "away": [
          "W",
          "L",
          "L",
          "L",
          "W"
        ]
      },
      "place_bet": "https://refpa3267686.top/L?tag=d_4524740m_1599c_&site=4524740&ad=1599"
    },
    {
      "teams": {
        "home": "Chrudim",
        "away": "Jihlava"
      },
      "prediction": {
        "type": "Away Win",
        "stake": "Small",
        "score": "1-2"
      },
      "form": {
        "home": [
          "L",
          "W",
          "L",
          "W",
          "L"
        ],
        "away": [
          "D",
          "L",
          "L",
          "W",
          "W"
        ]
      },
      "place_bet": "https://refpa3267686.top/L?tag=d_4524740m_1599c_&site=4524740&ad=1599"
    },
    {
      "teams": {
        "home": "FK Viagem Pribram",
        "away": "Usti nad Labem"
      },
      "prediction": {
        "type": "Draw",
        "stake": "Large",
        "score": "1-1"
      },
      "form": {
        "home": [
          "W",
          "L",
          "L",
          "L",
          "L"
        ],
        "away": [
          "W",
          "W",
          "W",
          "W",
          "W"
        ]
      },
      "place_bet": "https://refpa3267686.top/L?tag=d_4524740m_1599c_&site=4524740&ad=1599"
    },
    {
      "teams": {
        "home": "SK Lisen",
        "away": "FC Brno"
      },
      "prediction": {
        "type": "Home Win",
        "stake": "Large",
        "score": "1-0"
      },
      "form": {
        "home": [
          "W",
          "L",
          "W",
          "L",
          "L"
        ],
        "away": [
          "D",
          "W",
          "W",
          "W",
          "W"
        ]
      },
      "place_bet": "https://refpa3267686.top/L?tag=d_4524740m_1599c_&site=4524740&ad=1599"
    },
    {
      "teams": {
        "home": "Sk Prostejov",
        "away": "Slavia Prague II"
      },
      "prediction": {
        "type": "Home Win",
        "stake": "Large",
        "score": "1-0"
      },
      "form": {
        "home": [
          "L",
          "L",
          "W",
          "D",
          "L"
        ],
        "away": [
          "W",
          "W",
          "L",
          "L",
          "W"
        ]
      },
      "place_bet": "https://refpa3267686.top/L?tag=d_4524740m_1599c_&site=4524740&ad=1599"
    },
    {
      "teams": {
        "home": "Sparta Prague II",
        "away": "SK Hanacka Slavia Kromeriz"
      },
      "prediction": {
        "type": "Away Win",
        "stake": "Medium",
        "score": "0-1"
      },
      "form": {
        "home": [
          "L",
          "L",
          "L",
          "W",
          "L"
        ],
        "away": [
          "L",
          "L",
          "L",
          "L",
          "L"
        ]
      },
      "place_bet": "https://refpa3267686.top/L?tag=d_4524740m_1599c_&site=4524740&ad=1599"
    },
    {
      "teams": {
        "home": "Taborsko",
        "away": "Banik Ostrava II"
      },
      "prediction": {
        "type": "Away Win",
        "stake": "Small",
        "score": "1-2"
      },
      "form": {
        "home": [
          "L",
          "W",
          "W",
          "W",
          "L"
        ],
        "away": [
          "L",
          "W",
          "W",
          "D",
          "W"
        ]
      },
      "place_bet": "https://refpa3267686.top/L?tag=d_4524740m_1599c_&site=4524740&ad=1599"
    },
    {
      "teams": {
        "home": "FC Copenhagen",
        "away": "AGF Aarhus"
      },
      "prediction": {
        "type": "Draw",
        "stake": "Large",
        "score": "1-1"
      },
      "form": {
        "home": [
          "W",
          "W",
          "W",
          "W",
          "W"
        ],
        "away": [
          "L",
          "L",
          "D",
          "L",
          "D"
        ]
      },
      "place_bet": "stake.com/?c=Z6Kt1NA0"
    },
    {
      "teams": {
        "home": "Viborg",
        "away": "Sonderjyske"
      },
      "prediction": {
        "type": "Away Win",
        "stake": "Small",
        "score": "1-2"
      },
      "form": {
        "home": [
          "L",
          "W",
          "L",
          "L",
          "W"
        ],
        "away": [
          "W",
          "W",
          "D",
          "L",
          "W"
        ]
      },
      "place_bet": "stake.com/?c=Z6Kt1NA0"
    },
    {
      "teams": {
        "home": "Hobro",
        "away": "B93 Copenhagen"
      },
      "prediction": {
        "type": "Home Win",
        "stake": "Medium",
        "score": "1-0"
      },
      "form": {
        "home": [
          "L",
          "W",
          "L",
          "D",
          "D"
        ],
        "away": [
          "L",
          "L",
          "D",
          "D",
          "L"
        ]
      },
      "place_bet": "stake.com/?c=Z6Kt1NA0"
    },
    {
      "teams": {
        "home": "FC Inter",
        "away": "AC Oulu"
      },
      "prediction": {
        "type": "Home Win",
        "stake": "Large",
        "score": "3-0"
      },
      "form": {
        "home": [
          "W",
          "W",
          "D",
          "W",
          "W"
        ],
        "away": [
          "D",
          "W",
          "L",
          "W",
          "L"
        ]
      },
      "place_bet": "https://refpa3267686.top/L?tag=d_4524740m_1599c_&site=4524740&ad=1599"
    },
    {
      "teams": {
        "home": "GBK Kokkola",
        "away": "JS Hercules"
      },
      "prediction": {
        "type": "Home Win",
        "stake": "Large",
        "score": "3-2"
      },
      "form": {
        "home": [
          "L",
          "W",
          "W",
          "W",
          "W"
        ],
        "away": [
          "L",
          "L",
          "L",
          "W",
          "L"
        ]
      },
      "place_bet": "stake.com/?c=Z6Kt1NA0"
    },
    {
      "teams": {
        "home": "HAPK",
        "away": "VJS"
      },
      "prediction": {
        "type": "Away Win",
        "stake": "Large",
        "score": "1-3"
      },
      "form": {
        "home": [
          "L",
          "D",
          "L",
          "L",
          "L"
        ],
        "away": [
          "W",
          "D",
          "D",
          "D",
          "W"
        ]
      },
      "place_bet": "https://refpa3267686.top/L?tag=d_4524740m_1599c_&site=4524740&ad=1599"
    },
    {
      "teams": {
        "home": "HPS",
        "away": "TPV Tampere"
      },
      "prediction": {
        "type": "Away Win",
        "stake": "Small",
        "score": "0-1"
      },
      "form": {
        "home": [
          "W",
          "D",
          "L",
          "W",
          "W"
        ],
        "away": [
          "W",
          "D",
          "L",
          "W",
          "W"
        ]
      },
      "place_bet": "stake.com/?c=Z6Kt1NA0"
    },
    {
      "teams": {
        "home": "MuSa",
        "away": "NJS"
      },
      "prediction": {
        "type": "Home Win",
        "stake": "Large",
        "score": "3-0"
      },
      "form": {
        "home": [
          "L",
          "D",
          "L",
          "W",
          "L"
        ],
        "away": [
          "D",
          "W",
          "D",
          "L",
          "L"
        ]
      },
      "place_bet": "https://refpa3267686.top/L?tag=d_4524740m_1599c_&site=4524740&ad=1599"
    },
    {
      "teams": {
        "home": "OFK Banik Lehota pod Vtacnikom",
        "away": "Slovan Bratislava II"
      },
      "prediction": {
        "type": "Home Win",
        "stake": "Medium",
        "score": "1-0"
      },
      "form": {
        "home": [
          "L",
          "L",
          "D",
          "L",
          "D"
        ],
        "away": [
          "D",
          "D",
          "L",
          "L",
          "D"
        ]
      },
      "place_bet": "stake.com/?c=Z6Kt1NA0"
    },
    {
      "teams": {
        "home": "Pohronie",
        "away": "MSK Zilina II"
      },
      "prediction": {
        "type": "Home Win",
        "stake": "Medium",
        "score": "1-0"
      },
      "form": {
        "home": [
          "D",
          "L",
          "D",
          "D",
          "L"
        ],
        "away": [
          "D",
          "W",
          "D",
          "W",
          "L"
        ]
      },
      "place_bet": "https://refpa3267686.top/L?tag=d_4524740m_1599c_&site=4524740&ad=1599"
    },
    {
      "teams": {
        "home": "ViOn Zlate Moravce",
        "away": "Slavia TU Kosice"
      },
      "prediction": {
        "type": "Home Win",
        "stake": "Medium",
        "score": "2-1"
      },
      "form": {
        "home": [
          "L",
          "D",
          "L",
          "W",
          "D"
        ],
        "away": [
          "L",
          "L",
          "L",
          "D",
          "L"
        ]
      },
      "place_bet": "https://refpa3267686.top/L?tag=d_4524740m_1599c_&site=4524740&ad=1599"
    },
    {
      "teams": {
        "home": "Enkoping",
        "away": "AFC Eskilstuna"
      },
      "prediction": {
        "type": "Draw",
        "stake": "Large",
        "score": "2-2"
      },
      "form": {
        "home": [
          "W",
          "W",
          "L",
          "L",
          "D"
        ],
        "away": [
          "L",
          "W",
          "W",
          "D",
          "W"
        ]
      },
      "place_bet": "stake.com/?c=Z6Kt1NA0"
    },
    {
      "teams": {
        "home": "Rapperswil-Jona",
        "away": "Yverdon Sport"
      },
      "prediction": {
        "type": "Away Win",
        "stake": "Small",
        "score": "1-2"
      },
      "form": {
        "home": [
          "L",
          "L",
          "L",
          "W",
          "L"
        ],
        "away": [
          "L",
          "D",
          "W",
          "L",
          "W"
        ]
      },
      "place_bet": "https://refpa3267686.top/L?tag=d_4524740m_1599c_&site=4524740&ad=1599"
    },
    {
      "teams": {
        "home": "Wil",
        "away": "Etoile Carouge"
      },
      "prediction": {
        "type": "Home Win",
        "stake": "Small",
        "score": "1-0"
      },
      "form": {
        "home": [
          "W",
          "L",
          "W",
          "D",
          "L"
        ],
        "away": [
          "W",
          "L",
          "L",
          "L",
          "D"
        ]
      },
      "place_bet": "https://refpa3267686.top/L?tag=d_4524740m_1599c_&site=4524740&ad=1599"
    },
    {
      "teams": {
        "home": "Gaziantep BB",
        "away": "Galatasaray"
      },
      "prediction": {
        "type": "Away Win",
        "stake": "Large",
        "score": "1-2"
      },
      "form": {
        "home": [
          "L",
          "L",
          "D",
          "D",
          "D"
        ],
        "away": [
          "W",
          "W",
          "W",
          "W",
          "W"
        ]
      },
      "place_bet": "https://refpa3267686.top/L?tag=d_4524740m_1599c_&site=4524740&ad=1599"
    },
    {
      "teams": {
        "home": "Umraniyespor",
        "away": "Manisa Futbol Kulubu"
      },
      "prediction": {
        "type": "Home Win",
        "stake": "Medium",
        "score": "1-0"
      },
      "form": {
        "home": [
          "D",
          "W",
          "W",
          "L",
          "L"
        ],
        "away": [
          "L",
          "W",
          "W",
          "D",
          "W"
        ]
      },
      "place_bet": "stake.com/?c=Z6Kt1NA0"
    },
    {
      "teams": {
        "home": "Montana",
        "away": "Botev Vratsa"
      },
      "prediction": {
        "type": "Away Win",
        "stake": "Small",
        "score": "0-1"
      },
      "form": {
        "home": [
          "W",
          "D",
          "L",
          "D",
          "L"
        ],
        "away": [
          "W",
          "W",
          "D",
          "L",
          "D"
        ]
      },
      "place_bet": "https://refpa3267686.top/L?tag=d_4524740m_1599c_&site=4524740&ad=1599"
    },
    {
      "teams": {
        "home": "PFC Dobrudzha Dobrich",
        "away": "CSKA 1948"
      },
      "prediction": {
        "type": "Away Win",
        "stake": "Small",
        "score": "0-1"
      },
      "form": {
        "home": [
          "L",
          "W",
          "L",
          "W",
          "W"
        ],
        "away": [
          "W",
          "D",
          "W",
          "L",
          "W"
        ]
      },
      "place_bet": "stake.com/?c=Z6Kt1NA0"
    },
    {
      "teams": {
        "home": "FC Molodechno",
        "away": "Slavia Mozyr"
      },
      "prediction": {
        "type": "Away Win",
        "stake": "Large",
        "score": "0-1"
      },
      "form": {
        "home": [
          "L",
          "L",
          "D",
          "W",
          "L"
        ],
        "away": [
          "W",
          "D",
          "D",
          "W",
          "D"
        ]
      },
      "place_bet": "stake.com/?c=Z6Kt1NA0"
    },
    {
      "teams": {
        "home": "Dynamo Zagreb",
        "away": "Vukovar"
      },
      "prediction": {
        "type": "Home Win",
        "stake": "Large",
        "score": "2-0"
      },
      "form": {
        "home": [
          "W",
          "W",
          "D",
          "W",
          "W"
        ],
        "away": [
          "D",
          "W",
          "W",
          "W",
          "L"
        ]
      },
      "place_bet": "https://refpa3267686.top/L?tag=d_4524740m_1599c_&site=4524740&ad=1599"
    },
    {
      "teams": {
        "home": "Kazincbaricika SC",
        "away": "VSC Debrecen"
      },
      "prediction": {
        "type": "Home Win",
        "stake": "Medium",
        "score": "1-0"
      },
      "form": {
        "home": [
          "L",
          "L",
          "L",
          "D",
          "W"
        ],
        "away": [
          "D",
          "W",
          "L",
          "L",
          "L"
        ]
      },
      "place_bet": "https://refpa3267686.top/L?tag=d_4524740m_1599c_&site=4524740&ad=1599"
    },
    {
      "teams": {
        "home": "FK Panevezys",
        "away": "Dziugas"
      },
      "prediction": {
        "type": "Draw",
        "stake": "Large",
        "score": "1-1"
      },
      "form": {
        "home": [
          "L",
          "L",
          "W",
          "W",
          "W"
        ],
        "away": [
          "W",
          "L",
          "L",
          "W",
          "L"
        ]
      },
      "place_bet": "https://refpa3267686.top/L?tag=d_4524740m_1599c_&site=4524740&ad=1599"
    },
    {
      "teams": {
        "home": "Babrungas",
        "away": "Be1 NFA"
      },
      "prediction": {
        "type": "Home Win",
        "stake": "Medium",
        "score": "3-1"
      },
      "form": {
        "home": [
          "W",
          "W",
          "W",
          "W",
          "D"
        ],
        "away": [
          "W",
          "D",
          "L",
          "L",
          "L"
        ]
      },
      "place_bet": "https://refpa3267686.top/L?tag=d_4524740m_1599c_&site=4524740&ad=1599"
    },
    {
      "teams": {
        "home": "Neptunas Klaipeda",
        "away": "Transinvest"
      },
      "prediction": {
        "type": "Away Win",
        "stake": "Large",
        "score": "0-1"
      },
      "form": {
        "home": [
          "W",
          "W",
          "W",
          "L",
          "D"
        ],
        "away": [
          "W",
          "W",
          "W",
          "W",
          "D"
        ]
      },
      "place_bet": "stake.com/?c=Z6Kt1NA0"
    },
    {
      "teams": {
        "home": "Nevezis",
        "away": "Minija Kretinga"
      },
      "prediction": {
        "type": "Draw",
        "stake": "Medium",
        "score": "1-1"
      },
      "form": {
        "home": [
          "W",
          "D",
          "L",
          "L",
          "L"
        ],
        "away": [
          "L",
          "D",
          "L",
          "W",
          "L"
        ]
      },
      "place_bet": "stake.com/?c=Z6Kt1NA0"
    },
    {
      "teams": {
        "home": "Skendija 79",
        "away": "Shkupi Skopje"
      },
      "prediction": {
        "type": "Away Win",
        "stake": "Large",
        "score": "0-1"
      },
      "form": {
        "home": [
          "L",
          "D",
          "W",
          "W",
          "W"
        ],
        "away": [
          "D",
          "L",
          "L",
          "D",
          "W"
        ]
      },
      "place_bet": "stake.com/?c=Z6Kt1NA0"
    },
    {
      "teams": {
        "home": "Vardar",
        "away": "Pelister"
      },
      "prediction": {
        "type": "Home Win",
        "stake": "Medium",
        "score": "2-0"
      },
      "form": {
        "home": [
          "W",
          "W",
          "D",
          "W",
          "L"
        ],
        "away": [
          "W",
          "W",
          "W",
          "D",
          "L"
        ]
      },
      "place_bet": "stake.com/?c=Z6Kt1NA0"
    },
    {
      "teams": {
        "home": "Iskra Ribnita",
        "away": "Victoria Bardar"
      },
      "prediction": {
        "type": "Away Win",
        "stake": "Small",
        "score": "0-1"
      },
      "form": {
        "home": [
          "L",
          "W",
          "L",
          "W",
          "W"
        ],
        "away": [
          "L",
          "W",
          "L",
          "L",
          "W"
        ]
      },
      "place_bet": "https://refpa3267686.top/L?tag=d_4524740m_1599c_&site=4524740&ad=1599"
    },
    {
      "teams": {
        "home": "Sheriff Tiraspol II",
        "away": "Flacara Falesti"
      },
      "prediction": {
        "type": "Home Win",
        "stake": "Large",
        "score": "2-0"
      },
      "form": {
        "home": [
          "W",
          "L",
          "W",
          "D",
          "W"
        ],
        "away": [
          "L",
          "W",
          "L",
          "D",
          "L"
        ]
      },
      "place_bet": "stake.com/?c=Z6Kt1NA0"
    },
    {
      "teams": {
        "home": "Sporting Trestieni",
        "away": "Floresti"
      },
      "prediction": {
        "type": "Away Win",
        "stake": "Medium",
        "score": "0-1"
      },
      "form": {
        "home": [
          "W",
          "W",
          "L",
          "L",
          "L"
        ],
        "away": [
          "L",
          "L",
          "L",
          "W",
          "L"
        ]
      },
      "place_bet": "stake.com/?c=Z6Kt1NA0"
    },
    {
      "teams": {
        "home": "Zimbru II",
        "away": "FCM Ungheni"
      },
      "prediction": {
        "type": "Home Win",
        "stake": "Medium",
        "score": "1-0"
      },
      "form": {
        "home": [
          "W",
          "L",
          "W",
          "W",
          "L"
        ],
        "away": [
          "W",
          "W",
          "L",
          "L",
          "W"
        ]
      },
      "place_bet": "https://refpa3267686.top/L?tag=d_4524740m_1599c_&site=4524740&ad=1599"
    },
    {
      "teams": {
        "home": "Gornik Zabrze",
        "away": "Nieciecza"
      },
      "prediction": {
        "type": "Away Win",
        "stake": "Medium",
        "score": "0-2"
      },
      "form": {
        "home": [
          "L",
          "D",
          "W",
          "W",
          "L"
        ],
        "away": [
          "W",
          "W",
          "W",
          "L",
          "D"
        ]
      },
      "place_bet": "stake.com/?c=Z6Kt1NA0"
    },
    {
      "teams": {
        "home": "Korona Kielce",
        "away": "Radomiak Radom"
      },
      "prediction": {
        "type": "Home Win",
        "stake": "Medium",
        "score": "1-0"
      },
      "form": {
        "home": [
          "D",
          "D",
          "L",
          "L",
          "D"
        ],
        "away": [
          "D",
          "L",
          "W",
          "D",
          "W"
        ]
      },
      "place_bet": "stake.com/?c=Z6Kt1NA0"
    },
    {
      "teams": {
        "home": "Ruch Chorzow",
        "away": "Pogon Siedlce"
      },
      "prediction": {
        "type": "Home Win",
        "stake": "Small",
        "score": "1-0"
      },
      "form": {
        "home": [
          "D",
          "D",
          "D",
          "W",
          "L"
        ],
        "away": [
          "D",
          "W",
          "D",
          "L",
          "L"
        ]
      },
      "place_bet": "stake.com/?c=Z6Kt1NA0"
    },
    {
      "teams": {
        "home": "Slask Wroclaw",
        "away": "Miedz Legnica"
      },
      "prediction": {
        "type": "Home Win",
        "stake": "Medium",
        "score": "1-0"
      },
      "form": {
        "home": [
          "D",
          "D",
          "D",
          "L",
          "W"
        ],
        "away": [
          "W",
          "L",
          "L",
          "L",
          "L"
        ]
      },
      "place_bet": "https://refpa3267686.top/L?tag=d_4524740m_1599c_&site=4524740&ad=1599"
    },
    {
      "teams": {
        "home": "Metaloglobus Bucuresti",
        "away": "Dinamo Bucharest"
      },
      "prediction": {
        "type": "Home Win",
        "stake": "Small",
        "score": "1-0"
      },
      "form": {
        "home": [
          "W",
          "L",
          "D",
          "L",
          "L"
        ],
        "away": [
          "L",
          "D",
          "D",
          "L",
          "W"
        ]
      },
      "place_bet": "stake.com/?c=Z6Kt1NA0"
    },
    {
      "teams": {
        "home": "OFK Vrsac",
        "away": "FK Dinamo Jug"
      },
      "prediction": {
        "type": "Away Win",
        "stake": "Small",
        "score": "0-1"
      },
      "form": {
        "home": [
          "L",
          "L",
          "L",
          "W",
          "W"
        ],
        "away": [
          "L",
          "L",
          "L",
          "L",
          "W"
        ]
      },
      "place_bet": "https://refpa3267686.top/L?tag=d_4524740m_1599c_&site=4524740&ad=1599"
    },
    {
      "teams": {
        "home": "Bistrica",
        "away": "Rudar Velenje"
      },
      "prediction": {
        "type": "Home Win",
        "stake": "Small",
        "score": "2-0"
      },
      "form": {
        "home": [
          "D",
          "W",
          "W",
          "W",
          "L"
        ],
        "away": [
          "W",
          "D",
          "W",
          "L",
          "W"
        ]
      },
      "place_bet": "stake.com/?c=Z6Kt1NA0"
    },
    {
      "teams": {
        "home": "Nafta Lendava",
        "away": "ND Slovan"
      },
      "prediction": {
        "type": "Away Win",
        "stake": "Small",
        "score": "1-3"
      },
      "form": {
        "home": [
          "L",
          "L",
          "L",
          "L",
          "W"
        ],
        "away": [
          "D",
          "W",
          "W",
          "D",
          "W"
        ]
      },
      "place_bet": "https://refpa3267686.top/L?tag=d_4524740m_1599c_&site=4524740&ad=1599"
    },
    {
      "teams": {
        "home": "Poltava",
        "away": "Veres"
      },
      "prediction": {
        "type": "Home Win",
        "stake": "Medium",
        "score": "1-0"
      },
      "form": {
        "home": [
          "W",
          "L",
          "W",
          "W",
          "L"
        ],
        "away": [
          "L",
          "L",
          "L",
          "D",
          "L"
        ]
      },
      "place_bet": "stake.com/?c=Z6Kt1NA0"
    },
    {
      "teams": {
        "home": "Rukh Vinnyky",
        "away": "Dynamo Kiev"
      },
      "prediction": {
        "type": "Away Win",
        "stake": "Large",
        "score": "0-2"
      },
      "form": {
        "home": [
          "D",
          "W",
          "L",
          "D",
          "W"
        ],
        "away": [
          "D",
          "D",
          "W",
          "W",
          "W"
        ]
      },
      "place_bet": "https://refpa3267686.top/L?tag=d_4524740m_1599c_&site=4524740&ad=1599"
    },
    {
      "teams": {
        "home": "Vorskla",
        "away": "UCSA Tarasivka"
      },
      "prediction": {
        "type": "Home Win",
        "stake": "Medium",
        "score": "1-0"
      },
      "form": {
        "home": [
          "D",
          "D",
          "W",
          "L",
          "W"
        ],
        "away": [
          "L",
          "L",
          "D",
          "L",
          "W"
        ]
      },
      "place_bet": "stake.com/?c=Z6Kt1NA0"
    },
    {
      "teams": {
        "home": "Al Masry",
        "away": "Al Ittihad"
      },
      "prediction": {
        "type": "Home Win",
        "stake": "Large",
        "score": "1-0"
      },
      "form": {
        "home": [
          "L",
          "D",
          "L",
          "W",
          "W"
        ],
        "away": [
          "D",
          "D",
          "D",
          "L",
          "D"
        ]
      },
      "place_bet": "https://refpa3267686.top/L?tag=d_4524740m_1599c_&site=4524740&ad=1599"
    },
    {
      "teams": {
        "home": "Ceramica Cleopatra",
        "away": "Zamalek"
      },
      "prediction": {
        "type": "Away Win",
        "stake": "Large",
        "score": "1-2"
      },
      "form": {
        "home": [
          "D",
          "L",
          "W",
          "W",
          "L"
        ],
        "away": [
          "D",
          "D",
          "L",
          "W",
          "W"
        ]
      },
      "place_bet": "stake.com/?c=Z6Kt1NA0"
    },
    {
      "teams": {
        "home": "Wadi Degla",
        "away": "Pyramids FC"
      },
      "prediction": {
        "type": "Away Win",
        "stake": "Large",
        "score": "0-2"
      },
      "form": {
        "home": [
          "D",
          "L",
          "W",
          "D",
          "D"
        ],
        "away": [
          "W",
          "W",
          "D",
          "W",
          "W"
        ]
      },
      "place_bet": "stake.com/?c=Z6Kt1NA0"
    },
    {
      "teams": {
        "home": "Borneo Samarinda",
        "away": "Bhayangkara Surabaya United"
      },
      "prediction": {
        "type": "Draw",
        "stake": "Medium",
        "score": "1-1"
      },
      "form": {
        "home": [
          "W",
          "W",
          "W",
          "D",
          "W"
        ],
        "away": [
          "D",
          "W",
          "L",
          "W",
          "L"
        ]
      },
      "place_bet": "stake.com/?c=Z6Kt1NA0"
    },
    {
      "teams": {
        "home": "Persebaya Surabaya",
        "away": "PSIM Yogyakarta"
      },
      "prediction": {
        "type": "Home Win",
        "stake": "Medium",
        "score": "2-0"
      },
      "form": {
        "home": [
          "D",
          "D",
          "D",
          "D",
          "L"
        ],
        "away": [
          "D",
          "D",
          "D",
          "D",
          "L"
        ]
      },
      "place_bet": "stake.com/?c=Z6Kt1NA0"
    },
    {
      "teams": {
        "home": "PSM Makassar",
        "away": "Persijap Jepara"
      },
      "prediction": {
        "type": "Home Win",
        "stake": "Medium",
        "score": "1-0"
      },
      "form": {
        "home": [
          "L",
          "L",
          "W",
          "W",
          "W"
        ],
        "away": [
          "L",
          "L",
          "W",
          "W",
          "W"
        ]
      },
      "place_bet": "stake.com/?c=Z6Kt1NA0"
    },
    {
      "teams": {
        "home": "Johor",
        "away": "Selangor"
      },
      "prediction": {
        "type": "Home Win",
        "stake": "Medium",
        "score": "2-0"
      },
      "form": {
        "home": [
          "W",
          "W",
          "W",
          "W",
          "W"
        ],
        "away": [
          "D",
          "W",
          "L",
          "W",
          "W"
        ]
      },
      "place_bet": "stake.com/?c=Z6Kt1NA0"
    },
    {
      "teams": {
        "home": "Tigre",
        "away": "Huracan"
      },
      "prediction": {
        "type": "Home Win",
        "stake": "Medium",
        "score": "1-0"
      },
      "form": {
        "home": [
          "D",
          "L",
          "L",
          "W",
          "D"
        ],
        "away": [
          "W",
          "L",
          "L",
          "L",
          "W"
        ]
      },
      "place_bet": "stake.com/?c=Z6Kt1NA0"
    },
    {
      "teams": {
        "home": "Ferroviaria",
        "away": "Amazonas"
      },
      "prediction": {
        "type": "Home Win",
        "stake": "Large",
        "score": "2-0"
      },
      "form": {
        "home": [
          "L",
          "L",
          "D",
          "D",
          "W"
        ],
        "away": [
          "L",
          "W",
          "D",
          "D",
          "D"
        ]
      },
      "place_bet": "https://refpa3267686.top/L?tag=d_4524740m_1599c_&site=4524740&ad=1599"
    },
    {
      "teams": {
        "home": "Universitario de Vinto",
        "away": "Oriente Petrolero"
      },
      "prediction": {
        "type": "Home Win",
        "stake": "Medium",
        "score": "3-2"
      },
      "form": {
        "home": [
          "L",
          "L",
          "D",
          "W",
          "L"
        ],
        "away": [
          "L",
          "D",
          "L",
          "L",
          "W"
        ]
      },
      "place_bet": "stake.com/?c=Z6Kt1NA0"
    },
    {
      "teams": {
        "home": "Palestino",
        "away": "Deportes Iquique"
      },
      "prediction": {
        "type": "Home Win",
        "stake": "Large",
        "score": "2-0"
      },
      "form": {
        "home": [
          "D",
          "W",
          "D",
          "W",
          "D"
        ],
        "away": [
          "L",
          "L",
          "L",
          "W",
          "D"
        ]
      },
      "place_bet": "https://refpa3267686.top/L?tag=d_4524740m_1599c_&site=4524740&ad=1599"
    },
    {
      "teams": {
        "home": "Atletico Nacional",
        "away": "Alianza"
      },
      "prediction": {
        "type": "Home Win",
        "stake": "Large",
        "score": "1-0"
      },
      "form": {
        "home": [
          "W",
          "W",
          "L",
          "D",
          "D"
        ],
        "away": [
          "D",
          "W",
          "L",
          "D",
          "L"
        ]
      },
      "place_bet": "stake.com/?c=Z6Kt1NA0"
    },
    {
      "teams": {
        "home": "2 de Mayo",
        "away": "Sportivo Trinidense"
      },
      "prediction": {
        "type": "Home Win",
        "stake": "Medium",
        "score": "1-0"
      },
      "form": {
        "home": [
          "D",
          "W",
          "W",
          "L",
          "D"
        ],
        "away": [
          "W",
          "D",
          "L",
          "D",
          "W"
        ]
      },
      "place_bet": "stake.com/?c=Z6Kt1NA0"
    },
    {
      "teams": {
        "home": "Cerro Porteno",
        "away": "Nacional Asuncion"
      },
      "prediction": {
        "type": "Home Win",
        "stake": "Medium",
        "score": "2-0"
      },
      "form": {
        "home": [
          "W",
          "D",
          "W",
          "W",
          "W"
        ],
        "away": [
          "W",
          "W",
          "W",
          "L",
          "D"
        ]
      },
      "place_bet": "https://refpa3267686.top/L?tag=d_4524740m_1599c_&site=4524740&ad=1599"
    },
    {
      "teams": {
        "home": "Comerciantes Unidos",
        "away": "Cienciano"
      },
      "prediction": {
        "type": "Away Win",
        "stake": "Small",
        "score": "0-2"
      },
      "form": {
        "home": [
          "L",
          "L",
          "L",
          "D",
          "L"
        ],
        "away": [
          "L",
          "L",
          "D",
          "L",
          "W"
        ]
      },
      "place_bet": "stake.com/?c=Z6Kt1NA0"
    },
    {
      "teams": {
        "home": "Torque",
        "away": "Boston River"
      },
      "prediction": {
        "type": "Home Win",
        "stake": "Small",
        "score": "1-0"
      },
      "form": {
        "home": [
          "W",
          "D",
          "L",
          "D",
          "L"
        ],
        "away": [
          "D",
          "L",
          "W",
          "L",
          "W"
        ]
      },
      "place_bet": "https://refpa3267686.top/L?tag=d_4524740m_1599c_&site=4524740&ad=1599"
    },
    {
      "teams": {
        "home": "Dalian Yingbo",
        "away": "Chengdu Rongcheng"
      },
      "prediction": {
        "type": "Away Win",
        "stake": "Small",
        "score": "0-2"
      },
      "form": {
        "home": [
          "L",
          "W",
          "W",
          "W",
          "W"
        ],
        "away": [
          "W",
          "D",
          "L",
          "W",
          "W"
        ]
      },
      "place_bet": "https://refpa3267686.top/L?tag=d_4524740m_1599c_&site=4524740&ad=1599"
    },
    {
      "teams": {
        "home": "Henan Songshan Longmen",
        "away": "Sichuan Jiuniu"
      },
      "prediction": {
        "type": "Home Win",
        "stake": "Large",
        "score": "3-0"
      },
      "form": {
        "home": [
          "L",
          "D",
          "D",
          "L",
          "L"
        ],
        "away": [
          "L",
          "L",
          "W",
          "L",
          "L"
        ]
      },
      "place_bet": "stake.com/?c=Z6Kt1NA0"
    },
    {
      "teams": {
        "home": "Al Faysali",
        "away": "Al Salt"
      },
      "prediction": {
        "type": "Home Win",
        "stake": "Medium",
        "score": "1-0"
      },
      "form": {
        "home": [
          "W",
          "W",
          "D",
          "W",
          "W"
        ],
        "away": [
          "W",
          "D",
          "W",
          "L",
          "D"
        ]
      },
      "place_bet": "stake.com/?c=Z6Kt1NA0"
    },
    {
      "teams": {
        "home": "Shabab Al Ordun",
        "away": "Ramtha"
      },
      "prediction": {
        "type": "Draw",
        "stake": "Medium",
        "score": "1-1"
      },
      "form": {
        "home": [
          "W",
          "L",
          "W",
          "L",
          "D"
        ],
        "away": [
          "L",
          "D",
          "L",
          "D",
          "W"
        ]
      },
      "place_bet": "https://refpa3267686.top/L?tag=d_4524740m_1599c_&site=4524740&ad=1599"
    },
    {
      "teams": {
        "home": "FC Seoul",
        "away": "Daegu FC"
      },
      "prediction": {
        "type": "Home Win",
        "stake": "Large",
        "score": "2-0"
      },
      "form": {
        "home": [
          "D",
          "W",
          "W",
          "L",
          "W"
        ],
        "away": [
          "L",
          "D",
          "L",
          "L",
          "L"
        ]
      },
      "place_bet": "https://refpa3267686.top/L?tag=d_4524740m_1599c_&site=4524740&ad=1599"
    },
    {
      "teams": {
        "home": "Jeonbuk Motors",
        "away": "FC Anyang"
      },
      "prediction": {
        "type": "Home Win",
        "stake": "Medium",
        "score": "2-0"
      },
      "form": {
        "home": [
          "D",
          "W",
          "W",
          "W",
          "W"
        ],
        "away": [
          "L",
          "L",
          "L",
          "W",
          "L"
        ]
      },
      "place_bet": "https://refpa3267686.top/L?tag=d_4524740m_1599c_&site=4524740&ad=1599"
    },
    {
      "teams": {
        "home": "Bunyodkor",
        "away": "Shurtan"
      },
      "prediction": {
        "type": "Home Win",
        "stake": "Medium",
        "score": "3-0"
      },
      "form": {
        "home": [
          "D",
          "W",
          "W",
          "W",
          "W"
        ],
        "away": [
          "D",
          "W",
          "L",
          "L",
          "L"
        ]
      },
      "place_bet": "stake.com/?c=Z6Kt1NA0"
    },
    {
      "teams": {
        "home": "Qizilqum",
        "away": "Bukhara"
      },
      "prediction": {
        "type": "Home Win",
        "stake": "Medium",
        "score": "2-0"
      },
      "form": {
        "home": [
          "D",
          "D",
          "D",
          "W",
          "D"
        ],
        "away": [
          "D",
          "L",
          "W",
          "D",
          "L"
        ]
      },
      "place_bet": "stake.com/?c=Z6Kt1NA0"
    },
    {
      "teams": {
        "home": "Xorazm",
        "away": "Surkhon Termez"
      },
      "prediction": {
        "type": "Draw",
        "stake": "Small",
        "score": "1-1"
      },
      "form": {
        "home": [
          "L",
          "L",
          "L",
          "L",
          "W"
        ],
        "away": [
          "D",
          "L",
          "W",
          "D",
          "D"
        ]
      },
      "place_bet": "stake.com/?c=Z6Kt1NA0"
    }
  ]
}