{
  "scrape_info": {
    "timestamp": "2025-10-20T07:15:11.299277+00:00",
    "total_matches": 52,
    "source_url": "https://www.windrawwin.com/predictions/today/"
  },
  "matches": [
    {
      "teams": {
        "home": "West Ham",
        "away": "Brentford"
      },
      "prediction": {
        "type": "Home Win",
        "stake": "Large",
        "score": "1-0"
      },
      "form": {
        "home": [
          "W",
          "L",
          "L",
          "D",
          "L"
        ],
        "away": [
          "D",
          "D",
          "L",
          "W",
          "L"
        ]
      },
      "place_bet": "https://stake.com/?c=Z6Kt1NA0"
    },
    {
      "teams": {
        "home": "Cremonese",
        "away": "Udinese"
      },
      "prediction": {
        "type": "Away Win",
        "stake": "Small",
        "score": "0-1"
      },
      "form": {
        "home": [
          "W",
          "D",
          "D",
          "D",
          "L"
        ],
        "away": [
          "W",
          "L",
          "W",
          "L",
          "D"
        ]
      },
      "place_bet": "https://stake.com/?c=Z6Kt1NA0"
    },
    {
      "teams": {
        "home": "AC Carpi",
        "away": "Ascoli"
      },
      "prediction": {
        "type": "Away Win",
        "stake": "Large",
        "score": "1-2"
      },
      "form": {
        "home": [
          "W",
          "L",
          "L",
          "W",
          "W"
        ],
        "away": [
          "W",
          "W",
          "W",
          "W",
          "W"
        ]
      },
      "place_bet": "https://refpa3267686.top/L?tag=d_4524740m_1599c_&site=4524740&ad=1599"
    },
    {
      "teams": {
        "home": "Pontedera",
        "away": "Vis Pesaro"
      },
      "prediction": {
        "type": "Draw",
        "stake": "Medium",
        "score": "1-1"
      },
      "form": {
        "home": [
          "L",
          "L",
          "W",
          "D",
          "L"
        ],
        "away": [
          "D",
          "L",
          "D",
          "D",
          "D"
        ]
      },
      "place_bet": "https://stake.com/?c=Z6Kt1NA0"
    },
    {
      "teams": {
        "home": "Alaves",
        "away": "Valencia"
      },
      "prediction": {
        "type": "Home Win",
        "stake": "Large",
        "score": "3-0"
      },
      "form": {
        "home": [
          "W",
          "L",
          "D",
          "L",
          "W"
        ],
        "away": [
          "L",
          "W",
          "D",
          "L",
          "L"
        ]
      },
      "place_bet": "https://refpa3267686.top/L?tag=d_4524740m_1599c_&site=4524740&ad=1599"
    },
    {
      "teams": {
        "home": "Cadiz",
        "away": "Burgos"
      },
      "prediction": {
        "type": "Home Win",
        "stake": "Large",
        "score": "1-0"
      },
      "form": {
        "home": [
          "W",
          "W",
          "D",
          "L",
          "W"
        ],
        "away": [
          "W",
          "D",
          "W",
          "L",
          "L"
        ]
      },
      "place_bet": "https://refpa3267686.top/L?tag=d_4524740m_1599c_&site=4524740&ad=1599"
    },
    {
      "teams": {
        "home": "Nancy",
        "away": "Amiens"
      },
      "prediction": {
        "type": "Away Win",
        "stake": "Large",
        "score": "0-1"
      },
      "form": {
        "home": [
          "L",
          "L",
          "W",
          "L",
          "D"
        ],
        "away": [
          "D",
          "W",
          "L",
          "L",
          "L"
        ]
      },
      "place_bet": "https://stake.com/?c=Z6Kt1NA0"
    },
    {
      "teams": {
        "home": "AZ II",
        "away": "Willem II"
      },
      "prediction": {
        "type": "Away Win",
        "stake": "Large",
        "score": "2-3"
      },
      "form": {
        "home": [
          "L",
          "W",
          "D",
          "L",
          "L"
        ],
        "away": [
          "W",
          "W",
          "W",
          "L",
          "W"
        ]
      },
      "place_bet": "https://refpa3267686.top/L?tag=d_4524740m_1599c_&site=4524740&ad=1599"
    },
    {
      "teams": {
        "home": "FC Dordrecht",
        "away": "RKC Waalwijk"
      },
      "prediction": {
        "type": "Away Win",
        "stake": "Small",
        "score": "0-1"
      },
      "form": {
        "home": [
          "L",
          "D",
          "D",
          "W",
          "L"
        ],
        "away": [
          "W",
          "L",
          "W",
          "D",
          "L"
        ]
      },
      "place_bet": "https://stake.com/?c=Z6Kt1NA0"
    },
    {
      "teams": {
        "home": "Jong PSV",
        "away": "ADO Den Haag"
      },
      "prediction": {
        "type": "Away Win",
        "stake": "Large",
        "score": "0-1"
      },
      "form": {
        "home": [
          "W",
          "L",
          "D",
          "D",
          "D"
        ],
        "away": [
          "W",
          "W",
          "W",
          "W",
          "W"
        ]
      },
      "place_bet": "https://stake.com/?c=Z6Kt1NA0"
    },
    {
      "teams": {
        "home": "Roda JC",
        "away": "Almere City"
      },
      "prediction": {
        "type": "Home Win",
        "stake": "Large",
        "score": "3-1"
      },
      "form": {
        "home": [
          "L",
          "W",
          "D",
          "W",
          "W"
        ],
        "away": [
          "W",
          "L",
          "L",
          "D",
          "D"
        ]
      },
      "place_bet": "https://stake.com/?c=Z6Kt1NA0"
    },
    {
      "teams": {
        "home": "Bohemians",
        "away": "St Patricks"
      },
      "prediction": {
        "type": "Home Win",
        "stake": "Medium",
        "score": "1-0"
      },
      "form": {
        "home": [
          "D",
          "L",
          "W",
          "L",
          "L"
        ],
        "away": [
          "D",
          "D",
          "W",
          "L",
          "W"
        ]
      },
      "place_bet": "https://stake.com/?c=Z6Kt1NA0"
    },
    {
      "teams": {
        "home": "Chayka Peschanokopskoye",
        "away": "Ural Yekaterinburg"
      },
      "prediction": {
        "type": "Away Win",
        "stake": "Large",
        "score": "1-2"
      },
      "form": {
        "home": [
          "L",
          "L",
          "D",
          "D",
          "W"
        ],
        "away": [
          "D",
          "W",
          "D",
          "L",
          "L"
        ]
      },
      "place_bet": "https://refpa3267686.top/L?tag=d_4524740m_1599c_&site=4524740&ad=1599"
    },
    {
      "teams": {
        "home": "Chernomorets Novorossiysk",
        "away": "Neftekhimik"
      },
      "prediction": {
        "type": "Away Win",
        "stake": "Large",
        "score": "0-1"
      },
      "form": {
        "home": [
          "W",
          "L",
          "W",
          "W",
          "L"
        ],
        "away": [
          "W",
          "W",
          "W",
          "D",
          "L"
        ]
      },
      "place_bet": "https://stake.com/?c=Z6Kt1NA0"
    },
    {
      "teams": {
        "home": "Fakel Worenesch",
        "away": "Rotor Volgograd"
      },
      "prediction": {
        "type": "Draw",
        "stake": "Medium",
        "score": "1-1"
      },
      "form": {
        "home": [
          "L",
          "D",
          "D",
          "W",
          "W"
        ],
        "away": [
          "W",
          "D",
          "L",
          "D",
          "W"
        ]
      },
      "place_bet": "https://stake.com/?c=Z6Kt1NA0"
    },
    {
      "teams": {
        "home": "Torpedo Moscow",
        "away": "Shinnik Yaroslavl"
      },
      "prediction": {
        "type": "Away Win",
        "stake": "Small",
        "score": "0-1"
      },
      "form": {
        "home": [
          "L",
          "L",
          "W",
          "L",
          "D"
        ],
        "away": [
          "D",
          "D",
          "W",
          "L",
          "L"
        ]
      },
      "place_bet": "https://refpa3267686.top/L?tag=d_4524740m_1599c_&site=4524740&ad=1599"
    },
    {
      "teams": {
        "home": "Volga Ulyanovsk",
        "away": "Ufa"
      },
      "prediction": {
        "type": "Draw",
        "stake": "Large",
        "score": "1-1"
      },
      "form": {
        "home": [
          "W",
          "L",
          "D",
          "L",
          "L"
        ],
        "away": [
          "L",
          "D",
          "D",
          "D",
          "D"
        ]
      },
      "place_bet": "https://stake.com/?c=Z6Kt1NA0"
    },
    {
      "teams": {
        "home": "Chrudim",
        "away": "Taborsko"
      },
      "prediction": {
        "type": "Away Win",
        "stake": "Large",
        "score": "1-2"
      },
      "form": {
        "home": [
          "L",
          "D",
          "D",
          "W",
          "W"
        ],
        "away": [
          "W",
          "W",
          "D",
          "W",
          "W"
        ]
      },
      "place_bet": "https://stake.com/?c=Z6Kt1NA0"
    },
    {
      "teams": {
        "home": "Sonderjyske",
        "away": "Fredericia"
      },
      "prediction": {
        "type": "Home Win",
        "stake": "Medium",
        "score": "2-1"
      },
      "form": {
        "home": [
          "W",
          "L",
          "D",
          "L",
          "D"
        ],
        "away": [
          "L",
          "D",
          "L",
          "L",
          "L"
        ]
      },
      "place_bet": "https://refpa3267686.top/L?tag=d_4524740m_1599c_&site=4524740&ad=1599"
    },
    {
      "teams": {
        "home": "Fram Reykjavik",
        "away": "Stjarnan Gardabae"
      },
      "prediction": {
        "type": "Draw",
        "stake": "Medium",
        "score": "2-2"
      },
      "form": {
        "home": [
          "W",
          "D",
          "L",
          "W",
          "L"
        ],
        "away": [
          "W",
          "W",
          "D",
          "L",
          "L"
        ]
      },
      "place_bet": "https://stake.com/?c=Z6Kt1NA0"
    },
    {
      "teams": {
        "home": "Degerfors",
        "away": "Halmstads"
      },
      "prediction": {
        "type": "Draw",
        "stake": "Medium",
        "score": "1-1"
      },
      "form": {
        "home": [
          "D",
          "L",
          "W",
          "W",
          "D"
        ],
        "away": [
          "L",
          "D",
          "W",
          "W",
          "L"
        ]
      },
      "place_bet": "https://refpa3267686.top/L?tag=d_4524740m_1599c_&site=4524740&ad=1599"
    },
    {
      "teams": {
        "home": "IFK Goteborg",
        "away": "Mjallby"
      },
      "prediction": {
        "type": "Away Win",
        "stake": "Large",
        "score": "0-1"
      },
      "form": {
        "home": [
          "W",
          "W",
          "L",
          "W",
          "L"
        ],
        "away": [
          "W",
          "W",
          "D",
          "W",
          "W"
        ]
      },
      "place_bet": "https://refpa3267686.top/L?tag=d_4524740m_1599c_&site=4524740&ad=1599"
    },
    {
      "teams": {
        "home": "Hammarby Talang",
        "away": "Karlbergs"
      },
      "prediction": {
        "type": "Home Win",
        "stake": "Large",
        "score": "2-0"
      },
      "form": {
        "home": [
          "D",
          "W",
          "L",
          "W",
          "W"
        ],
        "away": [
          "L",
          "W",
          "W",
          "D",
          "D"
        ]
      },
      "place_bet": "https://stake.com/?c=Z6Kt1NA0"
    },
    {
      "teams": {
        "home": "Eyupspor",
        "away": "Kasimpasa"
      },
      "prediction": {
        "type": "Away Win",
        "stake": "Large",
        "score": "0-1"
      },
      "form": {
        "home": [
          "D",
          "L",
          "L",
          "D",
          "L"
        ],
        "away": [
          "W",
          "D",
          "D",
          "W",
          "D"
        ]
      },
      "place_bet": "https://refpa3267686.top/L?tag=d_4524740m_1599c_&site=4524740&ad=1599"
    },
    {
      "teams": {
        "home": "Istanbulspor",
        "away": "Bandirmaspor"
      },
      "prediction": {
        "type": "Home Win",
        "stake": "Medium",
        "score": "2-0"
      },
      "form": {
        "home": [
          "W",
          "W",
          "L",
          "D",
          "L"
        ],
        "away": [
          "D",
          "L",
          "L",
          "W",
          "W"
        ]
      },
      "place_bet": "https://stake.com/?c=Z6Kt1NA0"
    },
    {
      "teams": {
        "home": "Serik Belediyespor",
        "away": "Amed Sportif Faaliyetler"
      },
      "prediction": {
        "type": "Home Win",
        "stake": "Medium",
        "score": "2-1"
      },
      "form": {
        "home": [
          "W",
          "W",
          "D",
          "D",
          "D"
        ],
        "away": [
          "W",
          "L",
          "W",
          "L",
          "W"
        ]
      },
      "place_bet": "https://refpa3267686.top/L?tag=d_4524740m_1599c_&site=4524740&ad=1599"
    },
    {
      "teams": {
        "home": "Arda Kardzhali",
        "away": "Septemvri Sofia"
      },
      "prediction": {
        "type": "Home Win",
        "stake": "Medium",
        "score": "1-0"
      },
      "form": {
        "home": [
          "L",
          "W",
          "L",
          "L",
          "W"
        ],
        "away": [
          "W",
          "L",
          "L",
          "D",
          "D"
        ]
      },
      "place_bet": "https://stake.com/?c=Z6Kt1NA0"
    },
    {
      "teams": {
        "home": "Beroe Stara Zagora",
        "away": "Montana"
      },
      "prediction": {
        "type": "Home Win",
        "stake": "Large",
        "score": "2-0"
      },
      "form": {
        "home": [
          "D",
          "W",
          "D",
          "W",
          "L"
        ],
        "away": [
          "W",
          "W",
          "L",
          "L",
          "L"
        ]
      },
      "place_bet": "https://refpa3267686.top/L?tag=d_4524740m_1599c_&site=4524740&ad=1599"
    },
    {
      "teams": {
        "home": "Levadia Tallinn II",
        "away": "Nomme JK Kalju II"
      },
      "prediction": {
        "type": "Draw",
        "stake": "Medium",
        "score": "2-2"
      },
      "form": {
        "home": [
          "D",
          "W",
          "L",
          "D",
          "W"
        ],
        "away": [
          "D",
          "W",
          "L",
          "L",
          "W"
        ]
      },
      "place_bet": "https://stake.com/?c=Z6Kt1NA0"
    },
    {
      "teams": {
        "home": "Auda",
        "away": "FK Liepaja"
      },
      "prediction": {
        "type": "Draw",
        "stake": "Medium",
        "score": "2-2"
      },
      "form": {
        "home": [
          "L",
          "L",
          "W",
          "D",
          "L"
        ],
        "away": [
          "W",
          "W",
          "W",
          "D",
          "L"
        ]
      },
      "place_bet": "https://stake.com/?c=Z6Kt1NA0"
    },
    {
      "teams": {
        "home": "Wisla Plock",
        "away": "Nieciecza"
      },
      "prediction": {
        "type": "Home Win",
        "stake": "Large",
        "score": "1-0"
      },
      "form": {
        "home": [
          "W",
          "L",
          "L",
          "D",
          "D"
        ],
        "away": [
          "L",
          "D",
          "L",
          "L",
          "L"
        ]
      },
      "place_bet": "https://stake.com/?c=Z6Kt1NA0"
    },
    {
      "teams": {
        "home": "Puszcza Niepolomice",
        "away": "Wisla Krakow"
      },
      "prediction": {
        "type": "Away Win",
        "stake": "Large",
        "score": "0-1"
      },
      "form": {
        "home": [
          "D",
          "L",
          "W",
          "D",
          "D"
        ],
        "away": [
          "D",
          "W",
          "W",
          "D",
          "W"
        ]
      },
      "place_bet": "https://stake.com/?c=Z6Kt1NA0"
    },
    {
      "teams": {
        "home": "FC Petrolul Ploiesti",
        "away": "CFR Cluj"
      },
      "prediction": {
        "type": "Away Win",
        "stake": "Large",
        "score": "0-1"
      },
      "form": {
        "home": [
          "L",
          "L",
          "L",
          "L",
          "W"
        ],
        "away": [
          "D",
          "D",
          "D",
          "W",
          "D"
        ]
      },
      "place_bet": "https://stake.com/?c=Z6Kt1NA0"
    },
    {
      "teams": {
        "home": "Hermannstadt",
        "away": "Csikszereda"
      },
      "prediction": {
        "type": "Draw",
        "stake": "Large",
        "score": "2-2"
      },
      "form": {
        "home": [
          "L",
          "L",
          "W",
          "L",
          "L"
        ],
        "away": [
          "D",
          "D",
          "D",
          "W",
          "D"
        ]
      },
      "place_bet": "https://refpa3267686.top/L?tag=d_4524740m_1599c_&site=4524740&ad=1599"
    },
    {
      "teams": {
        "home": "FK Kudrivka",
        "away": "Metalist 1925"
      },
      "prediction": {
        "type": "Away Win",
        "stake": "Large",
        "score": "1-2"
      },
      "form": {
        "home": [
          "D",
          "L",
          "L",
          "W",
          "L"
        ],
        "away": [
          "W",
          "D",
          "W",
          "W",
          "D"
        ]
      },
      "place_bet": "https://stake.com/?c=Z6Kt1NA0"
    },
    {
      "teams": {
        "home": "UCSA Tarasivka",
        "away": "Levy Bereg Kiev"
      },
      "prediction": {
        "type": "Away Win",
        "stake": "Large",
        "score": "0-1"
      },
      "form": {
        "home": [
          "L",
          "D",
          "L",
          "W",
          "L"
        ],
        "away": [
          "L",
          "W",
          "D",
          "W",
          "W"
        ]
      },
      "place_bet": "https://refpa3267686.top/L?tag=d_4524740m_1599c_&site=4524740&ad=1599"
    },
    {
      "teams": {
        "home": "Bibiani Gold Stars",
        "away": "Heart of Lions"
      },
      "prediction": {
        "type": "Away Win",
        "stake": "Small",
        "score": "0-2"
      },
      "form": {
        "home": [
          "L",
          "L",
          "W",
          "L",
          "L"
        ],
        "away": [
          "W",
          "W",
          "W",
          "D",
          "D"
        ]
      },
      "place_bet": "https://stake.com/?c=Z6Kt1NA0"
    },
    {
      "teams": {
        "home": "Eleven Wonders",
        "away": "Karela"
      },
      "prediction": {
        "type": "Draw",
        "stake": "Medium",
        "score": "1-1"
      },
      "form": {
        "home": [
          "D",
          "L",
          "L",
          "L",
          "L"
        ],
        "away": [
          "W",
          "D",
          "W",
          "L",
          "D"
        ]
      },
      "place_bet": "https://stake.com/?c=Z6Kt1NA0"
    },
    {
      "teams": {
        "home": "Persis Solo",
        "away": "Malut United"
      },
      "prediction": {
        "type": "Away Win",
        "stake": "Small",
        "score": "1-3"
      },
      "form": {
        "home": [
          "D",
          "L",
          "L",
          "L",
          "D"
        ],
        "away": [
          "D",
          "L",
          "L",
          "W",
          "W"
        ]
      },
      "place_bet": "https://stake.com/?c=Z6Kt1NA0"
    },
    {
      "teams": {
        "home": "Semen Padang",
        "away": "Bhayangkara Surabaya United"
      },
      "prediction": {
        "type": "Away Win",
        "stake": "Small",
        "score": "0-1"
      },
      "form": {
        "home": [
          "D",
          "L",
          "L",
          "L",
          "L"
        ],
        "away": [
          "L",
          "W",
          "D",
          "W",
          "L"
        ]
      },
      "place_bet": "https://stake.com/?c=Z6Kt1NA0"
    },
    {
      "teams": {
        "home": "Deportivo Riestra",
        "away": "Instituto"
      },
      "prediction": {
        "type": "Home Win",
        "stake": "Large",
        "score": "1-0"
      },
      "form": {
        "home": [
          "W",
          "W",
          "W",
          "D",
          "D"
        ],
        "away": [
          "W",
          "D",
          "D",
          "D",
          "W"
        ]
      },
      "place_bet": "https://refpa3267686.top/L?tag=d_4524740m_1599c_&site=4524740&ad=1599"
    },
    {
      "teams": {
        "home": "Tigre",
        "away": "Barracas Central"
      },
      "prediction": {
        "type": "Away Win",
        "stake": "Medium",
        "score": "0-1"
      },
      "form": {
        "home": [
          "D",
          "W",
          "W",
          "D",
          "D"
        ],
        "away": [
          "W",
          "D",
          "L",
          "D",
          "D"
        ]
      },
      "place_bet": "https://stake.com/?c=Z6Kt1NA0"
    },
    {
      "teams": {
        "home": "Tristan Suarez",
        "away": "Estudiantes De Buenos Aires"
      },
      "prediction": {
        "type": "Away Win",
        "stake": "Medium",
        "score": "0-1"
      },
      "form": {
        "home": [
          "D",
          "L",
          "W",
          "W",
          "W"
        ],
        "away": [
          "W",
          "W",
          "W",
          "D",
          "W"
        ]
      },
      "place_bet": "https://stake.com/?c=Z6Kt1NA0"
    },
    {
      "teams": {
        "home": "Juventude RS",
        "away": "Bragantino"
      },
      "prediction": {
        "type": "Away Win",
        "stake": "Medium",
        "score": "0-1"
      },
      "form": {
        "home": [
          "D",
          "D",
          "L",
          "L",
          "L"
        ],
        "away": [
          "L",
          "D",
          "D",
          "W",
          "L"
        ]
      },
      "place_bet": "https://refpa3267686.top/L?tag=d_4524740m_1599c_&site=4524740&ad=1599"
    },
    {
      "teams": {
        "home": "Vasco da Gama",
        "away": "Fluminense"
      },
      "prediction": {
        "type": "Home Win",
        "stake": "Medium",
        "score": "3-1"
      },
      "form": {
        "home": [
          "W",
          "W",
          "L",
          "W",
          "W"
        ],
        "away": [
          "W",
          "D",
          "W",
          "L",
          "W"
        ]
      },
      "place_bet": "https://refpa3267686.top/L?tag=d_4524740m_1599c_&site=4524740&ad=1599"
    },
    {
      "teams": {
        "home": "Ferroviaria",
        "away": "Paysandu"
      },
      "prediction": {
        "type": "Home Win",
        "stake": "Small",
        "score": "1-0"
      },
      "form": {
        "home": [
          "D",
          "W",
          "L",
          "L",
          "D"
        ],
        "away": [
          "L",
          "W",
          "D",
          "L",
          "L"
        ]
      },
      "place_bet": "https://stake.com/?c=Z6Kt1NA0"
    },
    {
      "teams": {
        "home": "Sport Huancayo",
        "away": "Alianza Lima"
      },
      "prediction": {
        "type": "Home Win",
        "stake": "Small",
        "score": "2-0"
      },
      "form": {
        "home": [
          "L",
          "W",
          "L",
          "W",
          "L"
        ],
        "away": [
          "W",
          "L",
          "W",
          "L",
          "W"
        ]
      },
      "place_bet": "https://stake.com/?c=Z6Kt1NA0"
    },
    {
      "teams": {
        "home": "Plaza Colonia",
        "away": "Liverpool FC"
      },
      "prediction": {
        "type": "Away Win",
        "stake": "Large",
        "score": "0-1"
      },
      "form": {
        "home": [
          "L",
          "L",
          "D",
          "W",
          "L"
        ],
        "away": [
          "D",
          "L",
          "W",
          "W",
          "D"
        ]
      },
      "place_bet": "https://refpa3267686.top/L?tag=d_4524740m_1599c_&site=4524740&ad=1599"
    },
    {
      "teams": {
        "home": "Racing CM",
        "away": "Juventud Piedras"
      },
      "prediction": {
        "type": "Draw",
        "stake": "Large",
        "score": "1-1"
      },
      "form": {
        "home": [
          "D",
          "W",
          "D",
          "L",
          "D"
        ],
        "away": [
          "L",
          "L",
          "D",
          "D",
          "L"
        ]
      },
      "place_bet": "https://stake.com/?c=Z6Kt1NA0"
    },
    {
      "teams": {
        "home": "Beitar Jerusalem",
        "away": "Ashdod"
      },
      "prediction": {
        "type": "Away Win",
        "stake": "Large",
        "score": "1-2"
      },
      "form": {
        "home": [
          "D",
          "L",
          "W",
          "W",
          "W"
        ],
        "away": [
          "L",
          "L",
          "L",
          "W",
          "W"
        ]
      },
      "place_bet": "https://stake.com/?c=Z6Kt1NA0"
    },
    {
      "teams": {
        "home": "Bahla",
        "away": "Al Shabab"
      },
      "prediction": {
        "type": "Home Win",
        "stake": "Small",
        "score": "1-0"
      },
      "form": {
        "home": [
          "W",
          "W",
          "W",
          "W",
          "L"
        ],
        "away": [
          "L",
          "W",
          "W",
          "L",
          "W"
        ]
      },
      "place_bet": "https://refpa3267686.top/L?tag=d_4524740m_1599c_&site=4524740&ad=1599"
    },
    {
      "teams": {
        "home": "Viettel",
        "away": "Da Nang"
      },
      "prediction": {
        "type": "Home Win",
        "stake": "Large",
        "score": "2-0"
      },
      "form": {
        "home": [
          "W",
          "W",
          "D",
          "W",
          "D"
        ],
        "away": [
          "L",
          "L",
          "D",
          "W",
          "L"
        ]
      },
      "place_bet": "https://stake.com/?c=Z6Kt1NA0"
    }
  ]
}